KSA/KSA_4bit.v
`timescale 1ns/1ps

// 4-bit Kogge-Stone Adder - Gate Level
module kogge_stone_adder_4bit (
    input  [3:0] a,
    input  [3:0] b,
    input        cin,
    output [3:0] sum,
    output       cout
);

    // ---------------------------------------------------
    // Stage 0 : Bitwise Propagate / Generate
    // p = a ^ b , g = a & b
    // ---------------------------------------------------
    wire [3:0] p0, g0;

    xor xp0 (p0[0], a[0], b[0]);
    xor xp1 (p0[1], a[1], b[1]);
    xor xp2 (p0[2], a[2], b[2]);
    xor xp3 (p0[3], a[3], b[3]);

    and ag0 (g0[0], a[0], b[0]);
    and ag1 (g0[1], a[1], b[1]);
    and ag2 (g0[2], a[2], b[2]);
    and ag3 (g0[3], a[3], b[3]);

    // Fold carry-in into bit 0: G0 = g0 | (p0 & cin)
    wire t_cin, gc0;
    and ac0 (t_cin, p0[0], cin);
    or  oc0 (gc0, g0[0], t_cin);

    // ---------------------------------------------------
    // Stage 1 : prefix distance = 1
    // G1[i] = G0[i] | (P0[i] & G0[i-1])
    // P1[i] = P0[i] & P0[i-1]
    // ---------------------------------------------------
    wire [3:0] g1, p1;
    wire       t11, t12, t13;

    // bit 0 : pass-through
    buf bg10 (g1[0], gc0);
    buf bp10 (p1[0], p0[0]);

    // bit 1
    and a11 (t11, p0[1], gc0);
    or  o11 (g1[1], g0[1], t11);
    and ap11(p1[1], p0[1], p0[0]);

    // bit 2
    and a12 (t12, p0[2], g0[1]);
    or  o12 (g1[2], g0[2], t12);
    and ap12(p1[2], p0[2], p0[1]);

    // bit 3
    and a13 (t13, p0[3], g0[2]);
    or  o13 (g1[3], g0[3], t13);
    and ap13(p1[3], p0[3], p0[2]);

    // ---------------------------------------------------
    // Stage 2 : prefix distance = 2
    // G2[i] = G1[i] | (P1[i] & G1[i-2])
    // (P2 not needed: every group now reaches bit 0 / cin)
    // ---------------------------------------------------
    wire [3:0] g2;
    wire       t22, t23;

    // bits 0,1 : already final
    buf bg20 (g2[0], g1[0]);
    buf bg21 (g2[1], g1[1]);

    // bit 2
    and a22 (t22, p1[2], g1[0]);
    or  o22 (g2[2], g1[2], t22);

    // bit 3
    and a23 (t23, p1[3], g1[1]);
    or  o23 (g2[3], g1[3], t23);

    // ---------------------------------------------------
    // Stage 3 : Sum generation
    // sum[i] = p0[i] ^ carry[i]
    // carry[0]=cin, carry[1]=g2[0], carry[2]=g2[1], carry[3]=g2[2]
    // ---------------------------------------------------
    xor xs0 (sum[0], p0[0], cin);
    xor xs1 (sum[1], p0[1], g2[0]);
    xor xs2 (sum[2], p0[2], g2[1]);
    xor xs3 (sum[3], p0[3], g2[2]);

    // Carry out
    buf bco (cout, g2[3]);

endmodule

KSA/KSA_4bit_tb.v
`timescale 1ns/1ps

module tb_kogge_stone_adder_4bit;

    reg  [3:0] a, b;
    reg        cin;
    wire [3:0] sum;
    wire       cout;

    reg  [4:0] expected;
    integer    i, j, k;
    integer    errors;
    integer    total;

    // DUT
    kogge_stone_adder_4bit dut (
        .a   (a),
        .b   (b),
        .cin (cin),
        .sum (sum),
        .cout(cout)
    );

    // Waveform dump
    initial begin
        $dumpfile("kogge_stone_4bit.vcd");
        $dumpvars(0, tb_kogge_stone_adder_4bit);
    end

    initial begin
        errors = 0;
        total  = 0;

        $display("--------------------------------------------------");
        $display(" Time |  A   B  Cin | Cout Sum | Expected | Status");
        $display("--------------------------------------------------");

        // Exhaustive test
        for (i = 0; i < 16; i = i + 1) begin
            for (j = 0; j < 16; j = j + 1) begin
                for (k = 0; k < 2; k = k + 1) begin
                    a   = i[3:0];
                    b   = j[3:0];
                    cin = k[0];
                    #10;

                    expected = a + b + cin;
                    total    = total + 1;

                    if ({cout, sum} !== expected) begin
                        errors = errors + 1;
                        $display("%5t | %2d  %2d   %b  |  %b   %2d  |   %2d     | FAIL",
                                 $time, a, b, cin, cout, sum, expected);
                    end
                    else if (total <= 16) begin
                        // print only first few passes to keep log short
                        $display("%5t | %2d  %2d   %b  |  %b   %2d  |   %2d     | PASS",
                                 $time, a, b, cin, cout, sum, expected);
                    end
                end
            end
        end

        $display("--------------------------------------------------");
        $display(" Total tests : %0d", total);
        $display(" Errors      : %0d", errors);
        if (errors == 0)
            $display(" RESULT      : ALL TESTS PASSED");
        else
            $display(" RESULT      : TESTS FAILED");
        $display("--------------------------------------------------");

        $finish;
    end

endmodule

KSA/kogge_stone_4bit.vcd
$date
	Sun Oct 04 17:29:07 2026
$end
$version
	Icarus Verilog
$end
$timescale
	1ps
$end
$scope module tb_kogge_stone_adder_4bit $end
$var wire 4 ! sum [3:0] $end
$var wire 1 " cout $end
$var reg 4 # a [3:0] $end
$var reg 4 $ b [3:0] $end
$var reg 1 % cin $end
$var reg 5 & expected [4:0] $end
$var integer 32 ' errors [31:0] $end
$var integer 32 ( i [31:0] $end
$var integer 32 ) j [31:0] $end
$var integer 32 * k [31:0] $end
$var integer 32 + total [31:0] $end
$scope module dut $end
$var wire 4 , a [3:0] $end
$var wire 4 - b [3:0] $end
$var wire 1 % cin $end
$var wire 1 " cout $end
$var wire 1 . gc0 $end
$var wire 1 / t11 $end
$var wire 1 0 t12 $end
$var wire 1 1 t13 $end
$var wire 1 2 t22 $end
$var wire 1 3 t23 $end
$var wire 1 4 t_cin $end
$var wire 4 5 sum [3:0] $end
$var wire 4 6 p1 [3:0] $end
$var wire 4 7 p0 [3:0] $end
$var wire 4 8 g2 [3:0] $end
$var wire 4 9 g1 [3:0] $end
$var wire 4 : g0 [3:0] $end
$upscope $end
$upscope $end
$enddefinitions $end
#0
$dumpvars
b0 :
b0 9
b0 8
b0 7
b0 6
b0 5
04
03
02
01
00
0/
0.
b0 -
b0 ,
b0 +
b0 *
b0 )
b0 (
b0 '
bx &
0%
b0 $
b0 #
0"
b0 !
$end
#10000
b1 !
b1 5
1%
b1 *
b1 +
b0 &
#20000
b1 6
b1 7
b1 !
b1 5
0%
b1 $
b1 -
b1 )
b0 *
b10 +
b1 &
#30000
b1 8
b1 9
1.
14
b10 !
b10 5
1%
b1 *
b11 +
#40000
b0 8
b0 6
b0 9
0.
b10 7
04
b10 !
b10 5
0%
b10 $
b10 -
b10 )
b0 *
b100 +
b10 &
#50000
b11 !
b11 5
1%
b1 *
b101 +
#60000
b11 6
b11 7
b11 !
b11 5
0%
b11 $
b11 -
b11 )
b0 *
b110 +
b11 &
#70000
b11 8
b11 9
1/
1.
14
b100 !
b100 5
1%
b1 *
b111 +
#80000
b0 8
b0 6
b0 9
0/
0.
b100 7
04
b100 !
b100 5
0%
b100 $
b100 -
b100 )
b0 *
b1000 +
b100 &
#90000
b101 !
b101 5
1%
b1 *
b1001 +
#100000
b1 6
b101 7
b101 !
b101 5
0%
b101 $
b101 -
b101 )
b0 *
b1010 +
b101 &
#110000
b1 8
b1 9
1.
14
b110 !
b110 5
1%
b1 *
b1011 +
#120000
b0 8
b100 6
b0 9
0.
b110 7
04
b110 !
b110 5
0%
b110 $
b110 -
b110 )
b0 *
b1100 +
b110 &
#130000
b111 !
b111 5
1%
b1 *
b1101 +
#140000
b111 6
b111 7
b111 !
b111 5
0%
b111 $
b111 -
b111 )
b0 *
b1110 +
b111 &
#150000
b111 8
12
b11 9
1/
1.
14
b1000 !
b1000 5
1%
b1 *
b1111 +
#160000
b0 8
02
b0 6
b0 9
0/
0.
b1000 7
04
b1000 !
b1000 5
0%
b1000 $
b1000 -
b1000 )
b0 *
b10000 +
b1000 &
#170000
b1001 !
b1001 5
1%
b1 *
b10001 +
#180000
b1 6
b1001 7
b1001 !
b1001 5
0%
b1001 $
b1001 -
b1001 )
b0 *
b10010 +
b1001 &
#190000
b1 8
b1 9
1.
14
b1010 !
b1010 5
1%
b1 *
b10011 +
#200000
b0 8
b0 6
b0 9
0.
b1010 7
04
b1010 !
b1010 5
0%
b1010 $
b1010 -
b1010 )
b0 *
b10100 +
b1010 &
#210000
b1011 !
b1011 5
1%
b1 *
b10101 +
#220000
b11 6
b1011 7
b1011 !
b1011 5
0%
b1011 $
b1011 -
b1011 )
b0 *
b10110 +
b1011 &
#230000
b11 8
b11 9
1/
1.
14
b1100 !
b1100 5
1%
b1 *
b10111 +
#240000
b0 8
b1000 6
b0 9
0/
0.
b1100 7
04
b1100 !
b1100 5
0%
b1100 $
b1100 -
b1100 )
b0 *
b11000 +
b1100 &
#250000
b1101 !
b1101 5
1%
b1 *
b11001 +
#260000
b1001 6
b1101 7
b1101 !
b1101 5
0%
b1101 $
b1101 -
b1101 )
b0 *
b11010 +
b1101 &
#270000
b1 8
b1 9
1.
14
b1110 !
b1110 5
1%
b1 *
b11011 +
#280000
b0 8
b1100 6
b0 9
0.
b1110 7
04
b1110 !
b1110 5
0%
b1110 $
b1110 -
b1110 )
b0 *
b11100 +
b1110 &
#290000
b1111 !
b1111 5
1%
b1 *
b11101 +
#300000
b1111 6
b1111 7
b1111 !
b1111 5
0%
b1111 $
b1111 -
b1111 )
b0 *
b11110 +
b1111 &
#310000
1"
13
b1111 8
12
b11 9
1/
1.
14
b0 !
b0 5
1%
b1 *
b11111 +
#320000
0"
03
b0 8
02
b1 6
b0 9
0/
0.
b1 7
04
b1 !
b1 5
0%
b0 $
b0 -
b1 #
b1 ,
b1 (
b0 )
b0 *
b100000 +
b10000 &
#330000
b1 8
b1 9
1.
14
b10 !
b10 5
1%
b1 *
b100001 +
b1 &
#340000
b1 8
b0 6
b1 9
1.
b0 7
b1 :
04
b10 !
b10 5
0%
b1 $
b1 -
b1 )
b0 *
b100010 +
b10 &
#350000
b11 !
b11 5
1%
b1 *
b100011 +
#360000
b0 8
b0 9
b11 6
0.
b11 7
b0 :
b11 !
b11 5
0%
b10 $
b10 -
b10 )
b0 *
b100100 +
b11 &
#370000
b11 8
b11 9
1/
1.
14
b100 !
b100 5
1%
b1 *
b100101 +
#380000
b11 8
b0 6
b11 9
1/
1.
b10 7
b1 :
04
b100 !
b100 5
0%
b11 $
b11 -
b11 )
b0 *
b100110 +
b100 &
#390000
b101 !
b101 5
1%
b1 *
b100111 +
#400000
b0 8
b0 9
b1 6
0/
0.
b101 7
b0 :
b101 !
b101 5
0%
b100 $
b100 -
b100 )
b0 *
b101000 +
b101 &
#410000
b1 8
b1 9
1.
14
b110 !
b110 5
1%
b1 *
b101001 +
#420000
b1 8
b0 6
b1 9
1.
b100 7
b1 :
04
b110 !
b110 5
0%
b101 $
b101 -
b101 )
b0 *
b101010 +
b110 &
#430000
b111 !
b111 5
1%
b1 *
b101011 +
#440000
b0 8
b0 9
b111 6
0.
b111 7
b0 :
b111 !
b111 5
0%
b110 $
b110 -
b110 )
b0 *
b101100 +
b111 &
#450000
b111 8
12
b11 9
1/
1.
14
b1000 !
b1000 5
1%
b1 *
b101101 +
#460000
b111 8
12
b100 6
b11 9
1/
1.
b110 7
b1 :
04
b1000 !
b1000 5
0%
b111 $
b111 -
b111 )
b0 *
b101110 +
b1000 &
#470000
b1001 !
b1001 5
1%
b1 *
b101111 +
#480000
b0 8
02
b0 9
0/
b1 6
0.
b1001 7
b0 :
b1001 !
b1001 5
0%
b1000 $
b1000 -
b1000 )
b0 *
b110000 +
b1001 &
#490000
b1 8
b1 9
1.
14
b1010 !
b1010 5
1%
b1 *
b110001 +
#500000
b1 8
b0 6
b1 9
1.
b1000 7
b1 :
04
b1010 !
b1010 5
0%
b1001 $
b1001 -
b1001 )
b0 *
b110010 +
b1010 &
#510000
b1011 !
b1011 5
1%
b1 *
b110011 +
#520000
b0 8
b0 9
b11 6
0.
b1011 7
b0 :
b1011 !
b1011 5
0%
b1010 $
b1010 -
b1010 )
b0 *
b110100 +
b1011 &
#530000
b11 8
b11 9
1/
1.
14
b1100 !
b1100 5
1%
b1 *
b110101 +
#540000
b11 8
b0 6
b11 9
1/
1.
b1010 7
b1 :
04
b1100 !
b1100 5
0%
b1011 $
b1011 -
b1011 )
b0 *
b110110 +
b1100 &
#550000
b1101 !
b1101 5
1%
b1 *
b110111 +
#560000
0"
b0 8
03
b0 9
0/
b1001 6
0.
b1101 7
b0 :
b1101 !
b1101 5
0%
b1100 $
b1100 -
b1100 )
b0 *
b111000 +
b1101 &
#570000
b1 8
b1 9
1.
14
b1110 !
b1110 5
1%
b1 *
b111001 +
#580000
b1 8
b1000 6
b1 9
1.
b1100 7
b1 :
04
b1110 !
b1110 5
0%
b1101 $
b1101 -
b1101 )
b0 *
b111010 +
b1110 &
#590000
b1111 !
b1111 5
1%
b1 *
b111011 +
#600000
b0 8
b0 9
b1111 6
0.
b1111 7
b0 :
b1111 !
b1111 5
0%
b1110 $
b1110 -
b1110 )
b0 *
b111100 +
b1111 &
#610000
1"
13
b1111 8
12
b11 9
1/
1.
14
b0 !
b0 5
1%
b1 *
b111101 +
#620000
1"
13
b1111 8
12
b1100 6
b11 9
1/
1.
b1110 7
b1 :
04
b0 !
b0 5
0%
b1111 $
b1111 -
b1111 )
b0 *
b111110 +
b10000 &
#630000
b1 !
b1 5
1%
b1 *
b111111 +
#640000
0"
b0 8
02
03
b0 9
0/
b0 6
0.
b10 7
b0 :
b10 !
b10 5
0%
b0 $
b0 -
b10 #
b10 ,
b10 (
b0 )
b0 *
b1000000 +
b10001 &
#650000
b11 !
b11 5
1%
b1 *
b1000001 +
b10 &
#660000
b11 6
b11 7
b11 !
b11 5
0%
b1 $
b1 -
b1 )
b0 *
b1000010 +
b11 &
#670000
b11 8
b11 9
1/
1.
14
b100 !
b100 5
1%
b1 *
b1000011 +
#680000
b10 8
b0 6
b10 9
0/
0.
b0 7
b10 :
04
b100 !
b100 5
0%
b10 $
b10 -
b10 )
b0 *
b1000100 +
b100 &
#690000
b101 !
b101 5
1%
b1 *
b1000101 +
#700000
b1 6
b1 7
b101 !
b101 5
0%
b11 $
b11 -
b11 )
b0 *
b1000110 +
b101 &
#710000
b11 8
b11 9
1.
14
b110 !
b110 5
1%
b1 *
b1000111 +
#720000
b0 8
b100 6
b0 9
0.
b110 7
b0 :
04
b110 !
b110 5
0%
b100 $
b100 -
b100 )
b0 *
b1001000 +
b110 &
#730000
b111 !
b111 5
1%
b1 *
b1001001 +
#740000
b111 6
b111 7
b111 !
b111 5
0%
b101 $
b101 -
b101 )
b0 *
b1001010 +
b111 &
#750000
b111 8
12
b11 9
1/
1.
14
b1000 !
b1000 5
1%
b1 *
b1001011 +
#760000
b110 8
02
b0 6
10
b110 9
0/
0.
b100 7
b10 :
04
b1000 !
b1000 5
0%
b110 $
b110 -
b110 )
b0 *
b1001100 +
b1000 &
#770000
b1001 !
b1001 5
1%
b1 *
b1001101 +
#780000
b1 6
b101 7
b1001 !
b1001 5
0%
b111 $
b111 -
b111 )
b0 *
b1001110 +
b1001 &
#790000
b111 8
b111 9
1.
14
b1010 !
b1010 5
1%
b1 *
b1001111 +
#800000
b0 8
b0 6
00
b0 9
0.
b1010 7
b0 :
04
b1010 !
b1010 5
0%
b1000 $
b1000 -
b1000 )
b0 *
b1010000 +
b1010 &
#810000
b1011 !
b1011 5
1%
b1 *
b1010001 +
#820000
b11 6
b1011 7
b1011 !
b1011 5
0%
b1001 $
b1001 -
b1001 )
b0 *
b1010010 +
b1011 &
#830000
b11 8
b11 9
1/
1.
14
b1100 !
b1100 5
1%
b1 *
b1010011 +
#840000
b10 8
b0 6
b10 9
0/
0.
b1000 7
b10 :
04
b1100 !
b1100 5
0%
b1010 $
b1010 -
b1010 )
b0 *
b1010100 +
b1100 &
#850000
b1101 !
b1101 5
1%
b1 *
b1010101 +
#860000
b1 6
b1001 7
b1101 !
b1101 5
0%
b1011 $
b1011 -
b1011 )
b0 *
b1010110 +
b1101 &
#870000
b11 8
b11 9
1.
14
b1110 !
b1110 5
1%
b1 *
b1010111 +
#880000
b0 8
b1100 6
b0 9
0.
b1110 7
b0 :
04
b1110 !
b1110 5
0%
b1100 $
b1100 -
b1100 )
b0 *
b1011000 +
b1110 &
#890000
b1111 !
b1111 5
1%
b1 *
b1011001 +
#900000
b1111 6
b1111 7
b1111 !
b1111 5
0%
b1101 $
b1101 -
b1101 )
b0 *
b1011010 +
b1111 &
#910000
1"
13
b1111 8
12
b11 9
1/
1.
14
b0 !
b0 5
1%
b1 *
b1011011 +
#920000
b1110 8
02
b1000 6
10
b110 9
0/
0.
b1100 7
b10 :
04
b0 !
b0 5
0%
b1110 $
b1110 -
b1110 )
b0 *
b1011100 +
b10000 &
#930000
b1 !
b1 5
1%
b1 *
b1011101 +
#940000
b1001 6
b1101 7
b1 !
b1 5
0%
b1111 $
b1111 -
b1111 )
b0 *
b1011110 +
b10001 &
#950000
b1111 8
b111 9
1.
14
b10 !
b10 5
1%
b1 *
b1011111 +
#960000
0"
03
b0 8
b11 6
00
b0 9
0.
b11 7
b0 :
04
b11 !
b11 5
0%
b0 $
b0 -
b11 #
b11 ,
b11 (
b0 )
b0 *
b1100000 +
b10010 &
#970000
b11 8
b11 9
1/
1.
14
b100 !
b100 5
1%
b1 *
b1100001 +
b11 &
#980000
b11 8
b0 6
b11 9
1/
1.
b10 7
b1 :
04
b100 !
b100 5
0%
b1 $
b1 -
b1 )
b0 *
b1100010 +
b100 &
#990000
b101 !
b101 5
1%
b1 *
b1100011 +
#1000000
b10 8
b10 9
b1 6
0/
0.
b1 7
b10 :
b101 !
b101 5
0%
b10 $
b10 -
b10 )
b0 *
b1100100 +
b101 &
#1010000
b11 8
b11 9
1.
14
b110 !
b110 5
1%
b1 *
b1100101 +
#1020000
b11 8
b0 6
b11 9
1.
b0 7
b11 :
04
b110 !
b110 5
0%
b11 $
b11 -
b11 )
b0 *
b1100110 +
b110 &
#1030000
b111 !
b111 5
1%
b1 *
b1100111 +
#1040000
b0 8
b111 6
0.
b0 9
b111 7
b0 :
b111 !
b111 5
0%
b100 $
b100 -
b100 )
b0 *
b1101000 +
b111 &
#1050000
b111 8
12
b11 9
1/
1.
14
b1000 !
b1000 5
1%
b1 *
b1101001 +
#1060000
b111 8
12
b100 6
b11 9
1/
1.
b110 7
b1 :
04
b1000 !
b1000 5
0%
b101 $
b101 -
b101 )
b0 *
b1101010 +
b1000 &
#1070000
b1001 !
b1001 5
1%
b1 *
b1101011 +
#1080000
b110 8
02
b110 9
0/
b1 6
0.
10
b101 7
b10 :
b1001 !
b1001 5
0%
b110 $
b110 -
b110 )
b0 *
b1101100 +
b1001 &
#1090000
b111 8
b111 9
1.
14
b1010 !
b1010 5
1%
b1 *
b1101101 +
#1100000
b111 8
b0 6
b111 9
1.
b100 7
b11 :
04
b1010 !
b1010 5
0%
b111 $
b111 -
b111 )
b0 *
b1101110 +
b1010 &
#1110000
b1011 !
b1011 5
1%
b1 *
b1101111 +
#1120000
b0 8
b11 6
0.
b0 9
00
b1011 7
b0 :
b1011 !
b1011 5
0%
b1000 $
b1000 -
b1000 )
b0 *
b1110000 +
b1011 &
#1130000
b11 8
b11 9
1/
1.
14
b1100 !
b1100 5
1%
b1 *
b1110001 +
#1140000
b11 8
b0 6
b11 9
1/
1.
b1010 7
b1 :
04
b1100 !
b1100 5
0%
b1001 $
b1001 -
b1001 )
b0 *
b1110010 +
b1100 &
#1150000
b1101 !
b1101 5
1%
b1 *
b1110011 +
#1160000
b10 8
b10 9
b1 6
0/
0.
b1001 7
b10 :
b1101 !
b1101 5
0%
b1010 $
b1010 -
b1010 )
b0 *
b1110100 +
b1101 &
#1170000
b11 8
b11 9
1.
14
b1110 !
b1110 5
1%
b1 *
b1110101 +
#1180000
b11 8
b0 6
b11 9
1.
b1000 7
b11 :
04
b1110 !
b1110 5
0%
b1011 $
b1011 -
b1011 )
b0 *
b1110110 +
b1110 &
#1190000
b1111 !
b1111 5
1%
b1 *
b1110111 +
#1200000
b0 8
b1111 6
0.
b0 9
b1111 7
b0 :
b1111 !
b1111 5
0%
b1100 $
b1100 -
b1100 )
b0 *
b1111000 +
b1111 &
#1210000
1"
13
b1111 8
12
b11 9
1/
1.
14
b0 !
b0 5
1%
b1 *
b1111001 +
#1220000
1"
13
b1111 8
12
b1100 6
b11 9
1/
1.
b1110 7
b1 :
04
b0 !
b0 5
0%
b1101 $
b1101 -
b1101 )
b0 *
b1111010 +
b10000 &
#1230000
b1 !
b1 5
1%
b1 *
b1111011 +
#1240000
b1110 8
02
b110 9
0/
b1001 6
0.
10
b1101 7
b10 :
b1 !
b1 5
0%
b1110 $
b1110 -
b1110 )
b0 *
b1111100 +
b10001 &
#1250000
b1111 8
b111 9
1.
14
b10 !
b10 5
1%
b1 *
b1111101 +
#1260000
b1111 8
b1000 6
b111 9
1.
b1100 7
b11 :
04
b10 !
b10 5
0%
b1111 $
b1111 -
b1111 )
b0 *
b1111110 +
b10010 &
#1270000
b11 !
b11 5
1%
b1 *
b1111111 +
#1280000
0"
b0 8
03
b0 6
0.
b0 9
00
b100 7
b0 :
b100 !
b100 5
0%
b0 $
b0 -
b100 #
b100 ,
b100 (
b0 )
b0 *
b10000000 +
b10011 &
#1290000
b101 !
b101 5
1%
b1 *
b10000001 +
b100 &
#1300000
b1 6
b101 7
b101 !
b101 5
0%
b1 $
b1 -
b1 )
b0 *
b10000010 +
b101 &
#1310000
b1 8
b1 9
1.
14
b110 !
b110 5
1%
b1 *
b10000011 +
#1320000
b0 8
b100 6
b0 9
0.
b110 7
04
b110 !
b110 5
0%
b10 $
b10 -
b10 )
b0 *
b10000100 +
b110 &
#1330000
b111 !
b111 5
1%
b1 *
b10000101 +
#1340000
b111 6
b111 7
b111 !
b111 5
0%
b11 $
b11 -
b11 )
b0 *
b10000110 +
b111 &
#1350000
b111 8
12
b11 9
1/
1.
14
b1000 !
b1000 5
1%
b1 *
b10000111 +
#1360000
b100 8
02
b0 6
b100 9
0/
0.
b0 7
b100 :
04
b1000 !
b1000 5
0%
b100 $
b100 -
b100 )
b0 *
b10001000 +
b1000 &
#1370000
b1001 !
b1001 5
1%
b1 *
b10001001 +
#1380000
b1 6
b1 7
b1001 !
b1001 5
0%
b101 $
b101 -
b101 )
b0 *
b10001010 +
b1001 &
#1390000
b101 8
b101 9
1.
14
b1010 !
b1010 5
1%
b1 *
b10001011 +
#1400000
b100 8
b0 6
b100 9
0.
b10 7
04
b1010 !
b1010 5
0%
b110 $
b110 -
b110 )
b0 *
b10001100 +
b1010 &
#1410000
b1011 !
b1011 5
1%
b1 *
b10001101 +
#1420000
b11 6
b11 7
b1011 !
b1011 5
0%
b111 $
b111 -
b111 )
b0 *
b10001110 +
b1011 &
#1430000
b111 8
b111 9
1/
1.
14
b1100 !
b1100 5
1%
b1 *
b10001111 +
#1440000
b0 8
b1000 6
b0 9
0/
0.
b1100 7
b0 :
04
b1100 !
b1100 5
0%
b1000 $
b1000 -
b1000 )
b0 *
b10010000 +
b1100 &
#1450000
b1101 !
b1101 5
1%
b1 *
b10010001 +
#1460000
b1001 6
b1101 7
b1101 !
b1101 5
0%
b1001 $
b1001 -
b1001 )
b0 *
b10010010 +
b1101 &
#1470000
b1 8
b1 9
1.
14
b1110 !
b1110 5
1%
b1 *
b10010011 +
#1480000
b0 8
b1100 6
b0 9
0.
b1110 7
04
b1110 !
b1110 5
0%
b1010 $
b1010 -
b1010 )
b0 *
b10010100 +
b1110 &
#1490000
b1111 !
b1111 5
1%
b1 *
b10010101 +
#1500000
b1111 6
b1111 7
b1111 !
b1111 5
0%
b1011 $
b1011 -
b1011 )
b0 *
b10010110 +
b1111 &
#1510000
1"
13
b1111 8
12
b11 9
1/
1.
14
b0 !
b0 5
1%
b1 *
b10010111 +
#1520000
03
b1100 8
02
b0 6
11
b1100 9
0/
0.
b1000 7
b100 :
04
b0 !
b0 5
0%
b1100 $
b1100 -
b1100 )
b0 *
b10011000 +
b10000 &
#1530000
b1 !
b1 5
1%
b1 *
b10011001 +
#1540000
b1 6
b1001 7
b1 !
b1 5
0%
b1101 $
b1101 -
b1101 )
b0 *
b10011010 +
b10001 &
#1550000
b1101 8
b1101 9
1.
14
b10 !
b10 5
1%
b1 *
b10011011 +
#1560000
b1100 8
b0 6
b1100 9
0.
b1010 7
04
b10 !
b10 5
0%
b1110 $
b1110 -
b1110 )
b0 *
b10011100 +
b10010 &
#1570000
b11 !
b11 5
1%
b1 *
b10011101 +
#1580000
b11 6
b1011 7
b11 !
b11 5
0%
b1111 $
b1111 -
b1111 )
b0 *
b10011110 +
b10011 &
#1590000
b1111 8
b1111 9
1/
1.
14
b100 !
b100 5
1%
b1 *
b10011111 +
#1600000
0"
b0 8
b1 6
01
b0 9
0/
0.
b101 7
b0 :
04
b101 !
b101 5
0%
b0 $
b0 -
b101 #
b101 ,
b101 (
b0 )
b0 *
b10100000 +
b10100 &
#1610000
b1 8
b1 9
1.
14
b110 !
b110 5
1%
b1 *
b10100001 +
b101 &
#1620000
b1 8
b0 6
b1 9
1.
b100 7
b1 :
04
b110 !
b110 5
0%
b1 $
b1 -
b1 )
b0 *
b10100010 +
b110 &
#1630000
b111 !
b111 5
1%
b1 *
b10100011 +
#1640000
b0 8
b0 9
b111 6
0.
b111 7
b0 :
b111 !
b111 5
0%
b10 $
b10 -
b10 )
b0 *
b10100100 +
b111 &
#1650000
b111 8
12
b11 9
1/
1.
14
b1000 !
b1000 5
1%
b1 *
b10100101 +
#1660000
b111 8
12
b100 6
b11 9
1/
1.
b110 7
b1 :
04
b1000 !
b1000 5
0%
b11 $
b11 -
b11 )
b0 *
b10100110 +
b1000 &
#1670000
b1001 !
b1001 5
1%
b1 *
b10100111 +
#1680000
b100 8
02
0/
b1 6
0.
b100 9
b1 7
b100 :
b1001 !
b1001 5
0%
b100 $
b100 -
b100 )
b0 *
b10101000 +
b1001 &
#1690000
b101 8
b101 9
1.
14
b1010 !
b1010 5
1%
b1 *
b10101001 +
#1700000
b101 8
b0 6
b101 9
1.
b0 7
b101 :
04
b1010 !
b1010 5
0%
b101 $
b101 -
b101 )
b0 *
b10101010 +
b1010 &
#1710000
b1011 !
b1011 5
1%
b1 *
b10101011 +
#1720000
b100 8
b100 9
b11 6
0.
b11 7
b100 :
b1011 !
b1011 5
0%
b110 $
b110 -
b110 )
b0 *
b10101100 +
b1011 &
#1730000
b111 8
b111 9
1/
1.
14
b1100 !
b1100 5
1%
b1 *
b10101101 +
#1740000
b111 8
b0 6
b111 9
1/
1.
b10 7
b101 :
04
b1100 !
b1100 5
0%
b111 $
b111 -
b111 )
b0 *
b10101110 +
b1100 &
#1750000
b1101 !
b1101 5
1%
b1 *
b10101111 +
#1760000
0"
03
b0 8
0/
b1001 6
0.
b0 9
b1101 7
b0 :
b1101 !
b1101 5
0%
b1000 $
b1000 -
b1000 )
b0 *
b10110000 +
b1101 &
#1770000
b1 8
b1 9
1.
14
b1110 !
b1110 5
1%
b1 *
b10110001 +
#1780000
b1 8
b1000 6
b1 9
1.
b1100 7
b1 :
04
b1110 !
b1110 5
0%
b1001 $
b1001 -
b1001 )
b0 *
b10110010 +
b1110 &
#1790000
b1111 !
b1111 5
1%
b1 *
b10110011 +
#1800000
b0 8
b0 9
b1111 6
0.
b1111 7
b0 :
b1111 !
b1111 5
0%
b1010 $
b1010 -
b1010 )
b0 *
b10110100 +
b1111 &
#1810000
1"
13
b1111 8
12
b11 9
1/
1.
14
b0 !
b0 5
1%
b1 *
b10110101 +
#1820000
1"
13
b1111 8
12
b1100 6
b11 9
1/
1.
b1110 7
b1 :
04
b0 !
b0 5
0%
b1011 $
b1011 -
b1011 )
b0 *
b10110110 +
b10000 &
#1830000
b1 !
b1 5
1%
b1 *
b10110111 +
#1840000
b1100 8
02
03
0/
b1 6
0.
b1100 9
11
b1001 7
b100 :
b1 !
b1 5
0%
b1100 $
b1100 -
b1100 )
b0 *
b10111000 +
b10001 &
#1850000
b1101 8
b1101 9
1.
14
b10 !
b10 5
1%
b1 *
b10111001 +
#1860000
b1101 8
b0 6
b1101 9
1.
b1000 7
b101 :
04
b10 !
b10 5
0%
b1101 $
b1101 -
b1101 )
b0 *
b10111010 +
b10010 &
#1870000
b11 !
b11 5
1%
b1 *
b10111011 +
#1880000
b1100 8
b1100 9
b11 6
0.
b1011 7
b100 :
b11 !
b11 5
0%
b1110 $
b1110 -
b1110 )
b0 *
b10111100 +
b10011 &
#1890000
b1111 8
b1111 9
1/
1.
14
b100 !
b100 5
1%
b1 *
b10111101 +
#1900000
b1111 8
b0 6
b1111 9
1/
1.
b1010 7
b101 :
04
b100 !
b100 5
0%
b1111 $
b1111 -
b1111 )
b0 *
b10111110 +
b10100 &
#1910000
b101 !
b101 5
1%
b1 *
b10111111 +
#1920000
0"
b0 8
0/
b100 6
b0 9
01
0.
b110 7
b0 :
b110 !
b110 5
0%
b0 $
b0 -
b110 #
b110 ,
b110 (
b0 )
b0 *
b11000000 +
b10101 &
#1930000
b111 !
b111 5
1%
b1 *
b11000001 +
b110 &
#1940000
b111 6
b111 7
b111 !
b111 5
0%
b1 $
b1 -
b1 )
b0 *
b11000010 +
b111 &
#1950000
b111 8
12
b11 9
1/
1.
14
b1000 !
b1000 5
1%
b1 *
b11000011 +
#1960000
b110 8
02
b0 6
10
b110 9
0/
0.
b100 7
b10 :
04
b1000 !
b1000 5
0%
b10 $
b10 -
b10 )
b0 *
b11000100 +
b1000 &
#1970000
b1001 !
b1001 5
1%
b1 *
b11000101 +
#1980000
b1 6
b101 7
b1001 !
b1001 5
0%
b11 $
b11 -
b11 )
b0 *
b11000110 +
b1001 &
#1990000
b111 8
b111 9
1.
14
b1010 !
b1010 5
1%
b1 *
b11000111 +
#2000000
b100 8
b0 6
00
b100 9
0.
b10 7
b100 :
04
b1010 !
b1010 5
0%
b100 $
b100 -
b100 )
b0 *
b11001000 +
b1010 &
#2010000
b1011 !
b1011 5
1%
b1 *
b11001001 +
#2020000
b11 6
b11 7
b1011 !
b1011 5
0%
b101 $
b101 -
b101 )
b0 *
b11001010 +
b1011 &
