CLA/CLA_4bit.v
module CLA_4bit_gate_level (
    input  [3:0] a,
    input  [3:0] b,
    input        cin,
    output [3:0] sum,
    output       cout
);

    // Propagate and generate signals
    wire [3:0] p;
    wire [3:0] g;

    // Carry signals
    wire c1, c2, c3, c4;

    // Intermediate carry terms
    wire c1_term0;

    wire c2_term0;
    wire c2_term1;
    wire c2_term2;

    wire c3_term0;
    wire c3_term1;
    wire c3_term2;
    wire c3_term3;

    wire c4_term0;
    wire c4_term1;
    wire c4_term2;
    wire c4_term3;
    wire c4_term4;

    // Intermediate product terms for c3
    wire p2_p1;
    wire p2_p1_p0;

    // Intermediate product terms for c4
    wire p3_p2;
    wire p3_p2_p1;
    wire p3_p2_p1_p0;

    // -------------------------------------------------
    // Propagate and generate logic
    // -------------------------------------------------

    xor p0_gate (p[0], a[0], b[0]);
    xor p1_gate (p[1], a[1], b[1]);
    xor p2_gate (p[2], a[2], b[2]);
    xor p3_gate (p[3], a[3], b[3]);

    and g0_gate (g[0], a[0], b[0]);
    and g1_gate (g[1], a[1], b[1]);
    and g2_gate (g[2], a[2], b[2]);
    and g3_gate (g[3], a[3], b[3]);

    // -------------------------------------------------
    // Carry c1
    //
    // c1 = g0 + p0*cin
    // -------------------------------------------------

    and c1_and (c1_term0, p[0], cin);
    or  c1_or  (c1, g[0], c1_term0);

    // -------------------------------------------------
    // Carry c2
    //
    // c2 = g1 + p1*g0 + p1*p0*cin
    // -------------------------------------------------

    and c2_and0 (c2_term0, p[1], g[0]);
    and c2_and1 (c2_term1, p[1], p[0]);
    and c2_and2 (c2_term2, c2_term1, cin);

    or c2_or0 (c2, g[1], c2_term0, c2_term2);

    // -------------------------------------------------
    // Carry c3
    //
    // c3 = g2 + p2*g1 + p2*p1*g0 + p2*p1*p0*cin
    // -------------------------------------------------

    and p2p1_gate (p2_p1, p[2], p[1]);

    and c3_and0 (c3_term0, p[2], g[1]);
    and c3_and1 (c3_term1, p2_p1, g[0]);

    and p2p1p0_gate (p2_p1_p0, p2_p1, p[0]);
    and c3_and2 (c3_term2, p2_p1_p0, cin);

    or c3_or0 (
        c3,
        g[2],
        c3_term0,
        c3_term1,
        c3_term2
    );

    // -------------------------------------------------
    // Carry c4
    //
    // c4 = g3 + p3*g2 + p3*p2*g1
    //      + p3*p2*p1*g0 + p3*p2*p1*p0*cin
    // -------------------------------------------------

    and p3p2_gate (p3_p2, p[3], p[2]);

    and c4_and0 (c4_term0, p[3], g[2]);
    and c4_and1 (c4_term1, p3_p2, g[1]);

    and p3p2p1_gate (p3_p2_p1, p3_p2, p[1]);
    and c4_and2 (c4_term2, p3_p2_p1, g[0]);

    and p3p2p1p0_gate (p3_p2_p1_p0, p3_p2_p1, p[0]);
    and c4_and3 (c4_term3, p3_p2_p1_p0, cin);

    or c4_or0 (
        c4,
        g[3],
        c4_term0,
        c4_term1,
        c4_term2,
        c4_term3
    );

    // -------------------------------------------------
    // Sum logic
    //
    // sum[i] = p[i] XOR c[i]
    // -------------------------------------------------

    xor sum0_gate (sum[0], p[0], cin);
    xor sum1_gate (sum[1], p[1], c1);
    xor sum2_gate (sum[2], p[2], c2);
    xor sum3_gate (sum[3], p[3], c3);

    // Final carry output
    buf cout_gate (cout, c4);

endmodule

CLA/CLA_4bit_tb.v
`timescale 1ns/1ps

module tb;

    reg  [3:0] a;
    reg  [3:0] b;
    reg        cin;

    wire [3:0] sum;
    wire       cout;

    reg [4:0] expected;
    integer i;
    integer errors;

    // DUT: Device Under Test
    CLA_4bit_gate_level uut (
        .a    (a),
        .b    (b),
        .cin  (cin),
        .sum  (sum),
        .cout (cout)
    );

    initial begin

        // Create waveform file
        $dumpfile("CLA_4bit_gate_level.vcd");
        $dumpvars(0, tb);

        errors = 0;

        // Test all 4-bit input combinations
        for (i = 0; i < 512; i = i + 1) begin

            {a, b, cin} = i;

            #10;

            // Expected 5-bit result
            expected = {1'b0, a}
                     + {1'b0, b}
                     + {4'b0000, cin};

            // Compare actual and expected result
            if ({cout, sum} !== expected) begin

                errors = errors + 1;

                $display(
                    "ERROR: a=%b b=%b cin=%b | Expected=%b | Got=%b",
                    a, b, cin, expected, {cout, sum}
                );

            end

        end

        if (errors == 0)
            $display("ALL 512 TEST CASES PASSED");
        else
            $display("TEST FAILED: %0d errors found", errors);

        $finish;

    end

endmodule

CLA/CLA_4bit_gate_level.vcd
$date
	Sat Sep 12 23:33:35 2026
$end
$version
	Icarus Verilog
$end
$timescale
	1ps
$end
$scope module tb $end
$var wire 4 ! sum [3:0] $end
$var wire 1 " cout $end
$var reg 4 # a [3:0] $end
$var reg 4 $ b [3:0] $end
$var reg 1 % cin $end
$var reg 5 & expected [4:0] $end
$var integer 32 ' errors [31:0] $end
$var integer 32 ( i [31:0] $end
$scope module uut $end
$var wire 4 ) a [3:0] $end
$var wire 4 * b [3:0] $end
$var wire 1 + c1 $end
$var wire 1 , c1_term0 $end
$var wire 1 - c2 $end
$var wire 1 . c2_term0 $end
$var wire 1 / c2_term1 $end
$var wire 1 0 c2_term2 $end
$var wire 1 1 c3 $end
$var wire 1 2 c3_term0 $end
$var wire 1 3 c3_term1 $end
$var wire 1 4 c3_term2 $end
$var wire 1 5 c4 $end
$var wire 1 6 c4_term0 $end
$var wire 1 7 c4_term1 $end
$var wire 1 8 c4_term2 $end
$var wire 1 9 c4_term3 $end
$var wire 1 % cin $end
$var wire 1 " cout $end
$var wire 1 : p2_p1 $end
$var wire 1 ; p2_p1_p0 $end
$var wire 1 < p3_p2 $end
$var wire 1 = p3_p2_p1 $end
$var wire 1 > p3_p2_p1_p0 $end
$var wire 4 ? sum [3:0] $end
$var wire 4 @ p [3:0] $end
$var wire 4 A g [3:0] $end
$upscope $end
$upscope $end
$enddefinitions $end
#0
$dumpvars
b0 A
b0 @
b0 ?
0>
0=
0<
0;
0:
09
08
07
06
05
04
03
02
01
00
0/
0.
0-
0,
0+
b0 *
b0 )
b0 (
b0 '
bx &
0%
b0 $
b0 #
0"
b0 !
$end
#10000
b1 !
b1 ?
1%
b1 (
b0 &
#20000
b1 @
b1 !
b1 ?
b1 $
b1 *
0%
b10 (
b1 &
#30000
1+
1,
b10 !
b10 ?
1%
b11 (
#40000
b10 @
0+
0,
b10 !
b10 ?
b10 $
b10 *
0%
b100 (
b10 &
#50000
b11 !
b11 ?
1%
b101 (
#60000
1/
b11 @
b11 !
b11 ?
b11 $
b11 *
0%
b110 (
b11 &
#70000
1+
1-
1,
10
b100 !
b100 ?
1%
b111 (
#80000
0/
b100 @
0+
0-
0,
00
b100 !
b100 ?
b100 $
b100 *
0%
b1000 (
b100 &
#90000
b101 !
b101 ?
1%
b1001 (
#100000
b101 @
b101 !
b101 ?
b101 $
b101 *
0%
b1010 (
b101 &
#110000
1+
1,
b110 !
b110 ?
1%
b1011 (
#120000
1:
b110 @
0+
0,
b110 !
b110 ?
b110 $
b110 *
0%
b1100 (
b110 &
#130000
b111 !
b111 ?
1%
b1101 (
#140000
1/
1;
b111 @
b111 !
b111 ?
b111 $
b111 *
0%
b1110 (
b111 &
#150000
1+
1-
11
1,
10
14
b1000 !
b1000 ?
1%
b1111 (
#160000
0;
0/
0:
b1000 @
0+
0-
01
0,
00
04
b1000 !
b1000 ?
b1000 $
b1000 *
0%
b10000 (
b1000 &
#170000
b1001 !
b1001 ?
1%
b10001 (
#180000
b1001 @
b1001 !
b1001 ?
b1001 $
b1001 *
0%
b10010 (
b1001 &
#190000
1+
1,
b1010 !
b1010 ?
1%
b10011 (
#200000
b1010 @
0+
0,
b1010 !
b1010 ?
b1010 $
b1010 *
0%
b10100 (
b1010 &
#210000
b1011 !
b1011 ?
1%
b10101 (
#220000
1/
b1011 @
b1011 !
b1011 ?
b1011 $
b1011 *
0%
b10110 (
b1011 &
#230000
1+
1-
1,
10
b1100 !
b1100 ?
1%
b10111 (
#240000
0/
1<
b1100 @
0+
0-
0,
00
b1100 !
b1100 ?
b1100 $
b1100 *
0%
b11000 (
b1100 &
#250000
b1101 !
b1101 ?
1%
b11001 (
#260000
b1101 @
b1101 !
b1101 ?
b1101 $
b1101 *
0%
b11010 (
b1101 &
#270000
1+
1,
b1110 !
b1110 ?
1%
b11011 (
#280000
1:
1=
b1110 @
0+
0,
b1110 !
b1110 ?
b1110 $
b1110 *
0%
b11100 (
b1110 &
#290000
b1111 !
b1111 ?
1%
b11101 (
#300000
1/
1;
1>
b1111 @
b1111 !
b1111 ?
b1111 $
b1111 *
0%
b11110 (
b1111 &
#310000
1"
15
1+
1-
11
1,
10
14
19
b0 !
b0 ?
1%
b11111 (
#320000
0>
0;
0/
0=
0:
0<
0"
05
b1 @
0+
0-
01
0,
00
04
09
b1 !
b1 ?
b1 #
b1 )
b0 $
b0 *
0%
b100000 (
b10000 &
#330000
1+
1,
b10 !
b10 ?
1%
b100001 (
b1 &
#340000
b0 @
b1 A
1+
0,
b10 !
b10 ?
b1 $
b1 *
0%
b100010 (
b10 &
#350000
b11 !
b11 ?
1%
b100011 (
#360000
1/
0+
b11 @
b0 A
b11 !
b11 ?
b10 $
b10 *
0%
b100100 (
b11 &
#370000
1+
1-
1,
10
b100 !
b100 ?
1%
b100101 (
#380000
0/
1.
b10 @
b1 A
1+
1-
0,
00
b100 !
b100 ?
b11 $
b11 *
0%
b100110 (
b100 &
#390000
b101 !
b101 ?
1%
b100111 (
#400000
0-
0+
0.
b101 @
b0 A
b101 !
b101 ?
b100 $
b100 *
0%
b101000 (
b101 &
#410000
1+
1,
b110 !
b110 ?
1%
b101001 (
#420000
b100 @
b1 A
1+
0,
b110 !
b110 ?
b101 $
b101 *
0%
b101010 (
b110 &
#430000
b111 !
b111 ?
1%
b101011 (
#440000
1;
1/
1:
0+
b111 @
b0 A
b111 !
b111 ?
b110 $
b110 *
0%
b101100 (
b111 &
#450000
1+
1-
11
1,
10
14
b1000 !
b1000 ?
1%
b101101 (
#460000
0/
0;
1.
13
b110 @
b1 A
1+
1-
11
0,
00
04
b1000 !
b1000 ?
b111 $
b111 *
0%
b101110 (
b1000 &
#470000
b1001 !
b1001 ?
1%
b101111 (
#480000
0-
01
0:
0+
0.
03
b1001 @
b0 A
b1001 !
b1001 ?
b1000 $
b1000 *
0%
b110000 (
b1001 &
#490000
1+
1,
b1010 !
b1010 ?
1%
b110001 (
#500000
b1000 @
b1 A
1+
0,
b1010 !
b1010 ?
b1001 $
b1001 *
0%
b110010 (
b1010 &
#510000
b1011 !
b1011 ?
1%
b110011 (
#520000
1/
0+
b1011 @
b0 A
b1011 !
b1011 ?
b1010 $
b1010 *
0%
b110100 (
b1011 &
#530000
1+
1-
1,
10
b1100 !
b1100 ?
1%
b110101 (
#540000
0/
1.
b1010 @
b1 A
1+
1-
0,
00
b1100 !
b1100 ?
b1011 $
b1011 *
0%
b110110 (
b1100 &
#550000
b1101 !
b1101 ?
1%
b110111 (
#560000
0-
1<
0+
0.
b1101 @
b0 A
b1101 !
b1101 ?
b1100 $
b1100 *
0%
b111000 (
b1101 &
#570000
1+
1,
b1110 !
b1110 ?
1%
b111001 (
#580000
b1100 @
b1 A
1+
0,
b1110 !
b1110 ?
b1101 $
b1101 *
0%
b111010 (
b1110 &
#590000
b1111 !
b1111 ?
1%
b111011 (
#600000
1;
1>
1/
1:
1=
0+
b1111 @
b0 A
b1111 !
b1111 ?
b1110 $
b1110 *
0%
b111100 (
b1111 &
#610000
1"
15
1+
1-
11
1,
10
14
19
b0 !
b0 ?
1%
b111101 (
#620000
0/
0;
0>
1.
13
18
1"
15
b1110 @
b1 A
1+
1-
11
0,
00
04
09
b0 !
b0 ?
b1111 $
b1111 *
0%
b111110 (
b10000 &
#630000
b1 !
b1 ?
1%
b111111 (
#640000
0"
05
0=
0-
01
0:
0<
0+
0.
03
08
b10 @
b0 A
b10 !
b10 ?
b10 #
b10 )
b0 $
b0 *
0%
b1000000 (
b10001 &
#650000
b11 !
b11 ?
1%
b1000001 (
b10 &
#660000
1/
b11 @
b11 !
b11 ?
b1 $
b1 *
0%
b1000010 (
b11 &
#670000
1+
1-
1,
10
b100 !
b100 ?
1%
b1000011 (
#680000
0/
b0 @
b10 A
0+
1-
0,
00
b100 !
b100 ?
b10 $
b10 *
0%
b1000100 (
b100 &
#690000
b101 !
b101 ?
1%
b1000101 (
#700000
b1 @
b101 !
b101 ?
b11 $
b11 *
0%
b1000110 (
b101 &
#710000
1+
1,
b110 !
b110 ?
1%
b1000111 (
#720000
1:
0-
b110 @
b0 A
0+
0,
b110 !
b110 ?
b100 $
b100 *
0%
b1001000 (
b110 &
#730000
b111 !
b111 ?
1%
b1001001 (
#740000
1/
1;
b111 @
b111 !
b111 ?
b101 $
b101 *
0%
b1001010 (
b111 &
#750000
1+
1-
11
1,
10
14
b1000 !
b1000 ?
1%
b1001011 (
#760000
0;
0/
0:
12
b100 @
b10 A
0+
1-
11
0,
00
04
b1000 !
b1000 ?
b110 $
b110 *
0%
b1001100 (
b1000 &
#770000
b1001 !
b1001 ?
1%
b1001101 (
#780000
b101 @
b1001 !
b1001 ?
b111 $
b111 *
0%
b1001110 (
b1001 &
#790000
1+
1,
b1010 !
b1010 ?
1%
b1001111 (
#800000
01
0-
02
b1010 @
b0 A
0+
0,
b1010 !
b1010 ?
b1000 $
b1000 *
0%
b1010000 (
b1010 &
#810000
b1011 !
b1011 ?
1%
b1010001 (
#820000
1/
b1011 @
b1011 !
b1011 ?
b1001 $
b1001 *
0%
b1010010 (
b1011 &
#830000
1+
1-
1,
10
b1100 !
b1100 ?
1%
b1010011 (
#840000
0/
b1000 @
b10 A
0+
1-
0,
00
b1100 !
b1100 ?
b1010 $
b1010 *
0%
b1010100 (
b1100 &
#850000
b1101 !
b1101 ?
1%
b1010101 (
#860000
b1001 @
b1101 !
b1101 ?
b1011 $
b1011 *
0%
b1010110 (
b1101 &
#870000
1+
1,
b1110 !
b1110 ?
1%
b1010111 (
#880000
1=
1:
1<
0-
b1110 @
b0 A
0+
0,
b1110 !
b1110 ?
b1100 $
b1100 *
0%
b1011000 (
b1110 &
#890000
b1111 !
b1111 ?
1%
b1011001 (
#900000
1/
1;
1>
b1111 @
b1111 !
b1111 ?
b1101 $
b1101 *
0%
b1011010 (
b1111 &
#910000
1"
15
1+
1-
11
1,
10
14
19
b0 !
b0 ?
1%
b1011011 (
#920000
0;
0>
0/
0:
0=
12
17
1"
15
b1100 @
b10 A
0+
1-
11
0,
00
04
09
b0 !
b0 ?
b1110 $
b1110 *
0%
b1011100 (
b10000 &
#930000
b1 !
b1 ?
1%
b1011101 (
#940000
b1101 @
b1 !
b1 ?
b1111 $
b1111 *
0%
b1011110 (
b10001 &
#950000
1+
1,
b10 !
b10 ?
1%
b1011111 (
#960000
0"
05
01
1/
0<
0-
02
07
b11 @
b0 A
0+
0,
b11 !
b11 ?
b11 #
b11 )
b0 $
b0 *
0%
b1100000 (
b10010 &
#970000
1+
1-
1,
10
b100 !
b100 ?
1%
b1100001 (
b11 &
#980000
0/
1.
b10 @
b1 A
1+
1-
0,
00
b100 !
b100 ?
b1 $
b1 *
0%
b1100010 (
b100 &
#990000
b101 !
b101 ?
1%
b1100011 (
#1000000
0+
0.
b1 @
b10 A
b101 !
b101 ?
b10 $
b10 *
0%
b1100100 (
b101 &
#1010000
1+
1,
b110 !
b110 ?
1%
b1100101 (
#1020000
b0 @
b11 A
1+
0,
b110 !
b110 ?
b11 $
b11 *
0%
b1100110 (
b110 &
#1030000
b111 !
b111 ?
1%
b1100111 (
#1040000
1;
1/
1:
0+
0-
b111 @
b0 A
b111 !
b111 ?
b100 $
b100 *
0%
b1101000 (
b111 &
#1050000
1+
1-
11
1,
10
14
b1000 !
b1000 ?
1%
b1101001 (
#1060000
0/
0;
1.
13
b110 @
b1 A
1+
1-
11
0,
00
04
b1000 !
b1000 ?
b101 $
b101 *
0%
b1101010 (
b1000 &
#1070000
b1001 !
b1001 ?
1%
b1101011 (
#1080000
0:
0+
0.
03
12
b101 @
b10 A
b1001 !
b1001 ?
b110 $
b110 *
0%
b1101100 (
b1001 &
#1090000
1+
1,
b1010 !
b1010 ?
1%
b1101101 (
#1100000
b100 @
b11 A
1+
0,
b1010 !
b1010 ?
b111 $
b111 *
0%
b1101110 (
b1010 &
#1110000
b1011 !
b1011 ?
1%
b1101111 (
#1120000
01
1/
0+
0-
02
b1011 @
b0 A
b1011 !
b1011 ?
b1000 $
b1000 *
0%
b1110000 (
b1011 &
#1130000
1+
1-
1,
10
b1100 !
b1100 ?
1%
b1110001 (
#1140000
0/
1.
b1010 @
b1 A
1+
1-
0,
00
b1100 !
b1100 ?
b1001 $
b1001 *
0%
b1110010 (
b1100 &
#1150000
b1101 !
b1101 ?
1%
b1110011 (
#1160000
0+
0.
b1001 @
b10 A
b1101 !
b1101 ?
b1010 $
b1010 *
0%
b1110100 (
b1101 &
#1170000
1+
1,
b1110 !
b1110 ?
1%
b1110101 (
#1180000
b1000 @
b11 A
1+
0,
b1110 !
b1110 ?
b1011 $
b1011 *
0%
b1110110 (
b1110 &
#1190000
b1111 !
b1111 ?
1%
b1110111 (
#1200000
1;
1>
1/
1=
1:
1<
0+
0-
b1111 @
b0 A
b1111 !
b1111 ?
b1100 $
b1100 *
0%
b1111000 (
b1111 &
#1210000
1"
15
1+
1-
11
1,
10
14
19
b0 !
b0 ?
1%
b1111001 (
#1220000
0/
0;
0>
1.
13
18
1"
15
b1110 @
b1 A
1+
1-
11
0,
00
04
09
b0 !
b0 ?
b1101 $
b1101 *
0%
b1111010 (
b10000 &
#1230000
b1 !
b1 ?
1%
b1111011 (
#1240000
0:
0=
0+
0.
03
08
12
17
b1101 @
b10 A
b1 !
b1 ?
b1110 $
b1110 *
0%
b1111100 (
b10001 &
#1250000
1+
1,
b10 !
b10 ?
1%
b1111101 (
#1260000
b1100 @
b11 A
1+
0,
b10 !
b10 ?
b1111 $
b1111 *
0%
b1111110 (
b10010 &
#1270000
b11 !
b11 ?
1%
b1111111 (
#1280000
0"
05
01
0<
0+
0-
02
07
b100 @
b0 A
b100 !
b100 ?
b100 #
b100 )
b0 $
b0 *
0%
b10000000 (
b10011 &
#1290000
b101 !
b101 ?
1%
b10000001 (
b100 &
#1300000
b101 @
b101 !
b101 ?
b1 $
b1 *
0%
b10000010 (
b101 &
#1310000
1+
1,
b110 !
b110 ?
1%
b10000011 (
#1320000
1:
b110 @
0+
0,
b110 !
b110 ?
b10 $
b10 *
0%
b10000100 (
b110 &
#1330000
b111 !
b111 ?
1%
b10000101 (
#1340000
1/
1;
b111 @
b111 !
b111 ?
b11 $
b11 *
0%
b10000110 (
b111 &
#1350000
1+
1-
11
1,
10
14
b1000 !
b1000 ?
1%
b10000111 (
#1360000
0;
0/
0:
b0 @
b100 A
0+
0-
11
0,
00
04
b1000 !
b1000 ?
b100 $
b100 *
0%
b10001000 (
b1000 &
#1370000
b1001 !
b1001 ?
1%
b10001001 (
#1380000
b1 @
b1001 !
b1001 ?
b101 $
b101 *
0%
b10001010 (
b1001 &
#1390000
1+
1,
b1010 !
b1010 ?
1%
b10001011 (
#1400000
b10 @
0+
0,
b1010 !
b1010 ?
b110 $
b110 *
0%
b10001100 (
b1010 &
#1410000
b1011 !
b1011 ?
1%
b10001101 (
#1420000
1/
b11 @
b1011 !
b1011 ?
b111 $
b111 *
0%
b10001110 (
b1011 &
#1430000
1+
1-
1,
10
b1100 !
b1100 ?
1%
b10001111 (
#1440000
0/
1<
01
b1100 @
b0 A
0+
0-
0,
00
b1100 !
b1100 ?
b1000 $
b1000 *
0%
b10010000 (
b1100 &
#1450000
b1101 !
b1101 ?
1%
b10010001 (
#1460000
b1101 @
b1101 !
b1101 ?
b1001 $
b1001 *
0%
b10010010 (
b1101 &
#1470000
1+
1,
b1110 !
b1110 ?
1%
b10010011 (
#1480000
1:
1=
b1110 @
0+
0,
b1110 !
b1110 ?
b1010 $
b1010 *
0%
b10010100 (
b1110 &
#1490000
b1111 !
b1111 ?
1%
b10010101 (
#1500000
1/
1;
1>
b1111 @
b1111 !
b1111 ?
b1011 $
b1011 *
0%
b10010110 (
b1111 &
#1510000
1"
15
1+
1-
11
1,
10
14
19
b0 !
b0 ?
1%
b10010111 (
#1520000
0;
0>
0/
0=
0:
0<
16
1"
15
b1000 @
b100 A
0+
0-
11
0,
00
04
09
b0 !
b0 ?
b1100 $
b1100 *
0%
b10011000 (
b10000 &
#1530000
b1 !
b1 ?
1%
b10011001 (
#1540000
b1001 @
b1 !
b1 ?
b1101 $
b1101 *
0%
b10011010 (
b10001 &
#1550000
1+
1,
b10 !
b10 ?
1%
b10011011 (
#1560000
b1010 @
0+
0,
b10 !
b10 ?
b1110 $
b1110 *
0%
b10011100 (
b10010 &
#1570000
b11 !
b11 ?
1%
b10011101 (
#1580000
1/
b1011 @
b11 !
b11 ?
b1111 $
b1111 *
0%
b10011110 (
b10011 &
#1590000
1+
1-
1,
10
b100 !
b100 ?
1%
b10011111 (
#1600000
0"
05
0/
01
06
b101 @
b0 A
0+
0-
0,
00
b101 !
b101 ?
b101 #
b101 )
b0 $
b0 *
0%
b10100000 (
b10100 &
#1610000
1+
1,
b110 !
b110 ?
1%
b10100001 (
b101 &
#1620000
b100 @
b1 A
1+
0,
b110 !
b110 ?
b1 $
b1 *
0%
b10100010 (
b110 &
#1630000
b111 !
b111 ?
1%
b10100011 (
#1640000
1;
1/
1:
0+
b111 @
b0 A
b111 !
b111 ?
b10 $
b10 *
0%
b10100100 (
b111 &
#1650000
1+
1-
11
1,
10
14
b1000 !
b1000 ?
1%
b10100101 (
#1660000
0/
0;
1.
13
b110 @
b1 A
1+
1-
11
0,
00
04
b1000 !
b1000 ?
b11 $
b11 *
0%
b10100110 (
b1000 &
#1670000
b1001 !
b1001 ?
1%
b10100111 (
#1680000
0-
0:
0+
0.
03
b1 @
b100 A
b1001 !
b1001 ?
b100 $
b100 *
0%
b10101000 (
b1001 &
#1690000
1+
1,
b1010 !
b1010 ?
1%
b10101001 (
#1700000
b0 @
b101 A
1+
0,
b1010 !
b1010 ?
b101 $
b101 *
0%
b10101010 (
b1010 &
#1710000
b1011 !
b1011 ?
1%
b10101011 (
#1720000
1/
0+
b11 @
b100 A
b1011 !
b1011 ?
b110 $
b110 *
0%
b10101100 (
b1011 &
#1730000
1+
1-
1,
10
b1100 !
b1100 ?
1%
b10101101 (
#1740000
0/
1.
b10 @
b101 A
1+
1-
0,
00
b1100 !
b1100 ?
b111 $
b111 *
0%
b10101110 (
b1100 &
#1750000
b1101 !
b1101 ?
1%
b10101111 (
#1760000
0-
1<
0+
0.
01
b1101 @
b0 A
b1101 !
b1101 ?
b1000 $
b1000 *
0%
b10110000 (
b1101 &
#1770000
1+
1,
b1110 !
b1110 ?
1%
b10110001 (
#1780000
b1100 @
b1 A
1+
0,
b1110 !
b1110 ?
b1001 $
b1001 *
0%
b10110010 (
b1110 &
#1790000
b1111 !
b1111 ?
1%
b10110011 (
#1800000
1;
1>
1/
1:
1=
0+
b1111 @
b0 A
b1111 !
b1111 ?
b1010 $
b1010 *
0%
b10110100 (
b1111 &
#1810000
1"
15
1+
1-
11
1,
10
14
19
b0 !
b0 ?
1%
b10110101 (
#1820000
0/
0;
0>
1.
13
18
1"
15
b1110 @
b1 A
1+
1-
11
0,
00
04
09
b0 !
b0 ?
b1011 $
b1011 *
0%
b10110110 (
b10000 &
#1830000
b1 !
b1 ?
1%
b10110111 (
#1840000
0-
0=
0:
0<
0+
0.
03
08
16
b1001 @
b100 A
b1 !
b1 ?
b1100 $
b1100 *
0%
b10111000 (
b10001 &
#1850000
1+
1,
b10 !
b10 ?
1%
b10111001 (
#1860000
b1000 @
b101 A
1+
0,
b10 !
b10 ?
b1101 $
b1101 *
0%
b10111010 (
b10010 &
#1870000
b11 !
b11 ?
1%
b10111011 (
#1880000
1/
0+
b1011 @
b100 A
b11 !
b11 ?
b1110 $
b1110 *
0%
b10111100 (
b10011 &
#1890000
1+
1-
1,
10
b100 !
b100 ?
1%
b10111101 (
#1900000
0/
1.
b1010 @
b101 A
1+
1-
0,
00
b100 !
b100 ?
b1111 $
b1111 *
0%
b10111110 (
b10100 &
#1910000
b101 !
b101 ?
1%
b10111111 (
#1920000
0"
05
0-
1:
0+
0.
01
06
b110 @
b0 A
b110 !
b110 ?
b110 #
b110 )
b0 $
b0 *
0%
b11000000 (
b10101 &
#1930000
b111 !
b111 ?
1%
b11000001 (
b110 &
#1940000
1/
1;
b111 @
b111 !
b111 ?
b1 $
b1 *
0%
b11000010 (
b111 &
#1950000
1+
1-
11
1,
10
14
b1000 !
b1000 ?
1%
b11000011 (
#1960000
0;
0/
0:
12
b100 @
b10 A
0+
1-
11
0,
00
04
b1000 !
b1000 ?
b10 $
b10 *
0%
b11000100 (
b1000 &
#1970000
b1001 !
b1001 ?
1%
b11000101 (
#1980000
b101 @
b1001 !
b1001 ?
b11 $
b11 *
0%
b11000110 (
b1001 &
#1990000
1+
1,
b1010 !
b1010 ?
1%
b11000111 (
#2000000
0-
02
b10 @
b100 A
0+
0,
b1010 !
b1010 ?
b100 $
b100 *
0%
b11001000 (
b1010 &
#2010000
b1011 !
b1011 ?
1%
b11001001 (
#2020000
1/
b11 @
b1011 !
b1011 ?
b101 $
b101 *
0%
b11001010 (
b1011 &
#2030000
1+
1-
1,
10
b1100 !
b1100 ?
1%
b11001011 (
#2040000
0/
b0 @
b110 A
0+
1-
0,
00
b1100 !
b1100 ?
b110 $
b110 *
0%
b11001100 (
b1100 &
#2050000
b1101 !
b1101 ?
1%
b11001101 (
#2060000
b1 @
b1101 !
b1101 ?
b111 $
b111 *
0%
b11001110 (
b1101 &
#2070000
1+
1,
b1110 !
b1110 ?
1%
b11001111 (
#2080000
1=
1:
1<
0-
01
b1110 @
b0 A
0+
0,
b1110 !
b1110 ?
b1000 $
b1000 *
0%
b11010000 (
b1110 &
#2090000
b1111 !
b1111 ?
1%
b11010001 (
#2100000
1/
1;
1>
b1111 @
b1111 !
b1111 ?
b1001 $
b1001 *
0%
b11010010 (
b1111 &
#2110000
1"
15
1+
1-
11
1,
10
14
19
b0 !
b0 ?
1%
b11010011 (
#2120000
0;
0>
0/
0:
0=
12
17
1"
15
b1100 @
b10 A
0+
1-
11
0,
00
04
09
b0 !
b0 ?
b1010 $
b1010 *
0%
b11010100 (
b10000 &
#2130000
b1 !
b1 ?
1%
b11010101 (
#2140000
b1101 @
b1 !
b1 ?
b1011 $
b1011 *
0%
b11010110 (
b10001 &
#2150000
1+
1,
b10 !
b10 ?
1%
b11010111 (
#2160000
0<
0-
02
07
16
b1010 @
b100 A
0+
0,
b10 !
b10 ?
b1100 $
b1100 *
0%
b11011000 (
b10010 &
#2170000
b11 !
b11 ?
1%
b11011001 (
#2180000
1/
b1011 @
b11 !
b11 ?
b1101 $
b1101 *
0%
b11011010 (
b10011 &
#2190000
1+
1-
1,
10
b100 !
b100 ?
1%
b11011011 (
#2200000
0/
b1000 @
b110 A
0+
1-
0,
00
b100 !
b100 ?
b1110 $
b1110 *
0%
b11011100 (
b10100 &
#2210000
b101 !
b101 ?
1%
b11011101 (
#2220000
b1001 @
b101 !
b101 ?
b1111 $
b1111 *
0%
b11011110 (
b10101 &
#2230000
1+
1,
b110 !
b110 ?
1%
b11011111 (
#2240000
0"
05
1;
1/
1:
0-
01
06
b111 @
b0 A
0+
0,
b111 !
b111 ?
b111 #
b111 )
b0 $
b0 *
0%
b11100000 (
b10110 &
#2250000
1+
1-
11
1,
10
14
b1000 !
b1000 ?
1%
b11100001 (
b111 &
#2260000
0/
0;
1.
13
b110 @
b1 A
1+
1-
11
0,
00
04
b1000 !
b1000 ?
b1 $
b1 *
0%
b11100010 (
b1000 &
#2270000
b1001 !
b1001 ?
1%
b11100011 (
#2280000
0:
0+
0.
03
12
b101 @
b10 A
b1001 !
b1001 ?
b10 $
b10 *
0%
b11100100 (
b1001 &
#2290000
1+
1,
b1010 !
b1010 ?
1%
b11100101 (
#2300000
b100 @
b11 A
1+
0,
b1010 !
b1010 ?
b11 $
b11 *
0%
b11100110 (
b1010 &
#2310000
b1011 !
b1011 ?
1%
b11100111 (
#2320000
1/
0+
0-
02
b11 @
b100 A
b1011 !
b1011 ?
b100 $
b100 *
0%
b11101000 (
b1011 &
#2330000
1+
1-
1,
10
b1100 !
b1100 ?
1%
b11101001 (
#2340000
0/
1.
b10 @
b101 A
1+
1-
0,
00
b1100 !
b1100 ?
b101 $
b101 *
0%
b11101010 (
b1100 &
#2350000
b1101 !
b1101 ?
1%
b11101011 (
#2360000
0+
0.
b1 @
b110 A
b1101 !
b1101 ?
b110 $
b110 *
0%
b11101100 (
b1101 &
#2370000
1+
1,
b1110 !
b1110 ?
1%
b11101101 (
#2380000
b0 @
b111 A
1+
0,
b1110 !
b1110 ?
b111 $
b111 *
0%
b11101110 (
b1110 &
#2390000
b1111 !
b1111 ?
1%
b11101111 (
#2400000
1;
1>
1/
1=
1:
1<
0+
0-
01
b1111 @
b0 A
b1111 !
b1111 ?
b1000 $
b1000 *
0%
b11110000 (
b1111 &
#2410000
1"
15
1+
1-
11
1,
10
14
19
b0 !
b0 ?
1%
b11110001 (
#2420000
0/
0;
0>
1.
13
18
1"
15
b1110 @
b1 A
1+
1-
11
0,
00
04
09
b0 !
b0 ?
b1001 $
b1001 *
0%
b11110010 (
b10000 &
#2430000
b1 !
b1 ?
1%
b11110011 (
#2440000
0:
0=
0+
0.
03
08
12
17
b1101 @
b10 A
b1 !
b1 ?
b1010 $
b1010 *
0%
b11110100 (
b10001 &
#2450000
1+
1,
b10 !
b10 ?
1%
b11110101 (
#2460000
b1100 @
b11 A
1+
0,
b10 !
b10 ?
b1011 $
b1011 *
0%
b11110110 (
b10010 &
#2470000
b11 !
b11 ?
1%
b11110111 (
