RAC/RAC_4bit.v
module rac_4bit(
    input  [3:0] a,
    input  [3:0] b,
    input        cin,
    output [3:0] sum,
    output       cout
);

    wire c1, c2, c3;

    // Bit 0 (LSB)
    FA_1bit uut0 (
        .a(a[0]),
        .b(b[0]),
        .cin(cin),
        .sum(sum[0]),
        .cout(c1)
    );

    // Bit 1  
    FA_1bit uut1 (
        .a(a[1]),
        .b(b[1]),
        .cin(c1),
        .sum(sum[1]),
        .cout(c2)
    );

    // Bit 2
    FA_1bit uut2 (
        .a(a[2]),
        .b(b[2]),
        .cin(c2),
        .sum(sum[2]),
        .cout(c3)
    );

    // Bit 3 (MSB)
    FA_1bit uut3 (
        .a(a[3]),
        .b(b[3]),
        .cin(c3),
        .sum(sum[3]),
        .cout(cout)
    );

endmodule


module FA_1bit(
    input a, b, cin,
    output sum, cout
);

    wire s1, c1, c2;

    xor(s1, a, b);
    xor(sum, s1, cin);

    and(c1, a, b);
    and(c2, s1, cin);

    or(cout, c1, c2);

endmodule

RAC/RAC_4bit_tb.v
`timescale 1ns/1ps

module tb;
reg [3:0] a;
reg [3:0] b;
reg cin;
wire [3:0] sum;
wire cout;
rac_4bit uut(
            .a(a),
            .b(b),
            .cin(cin),
            .sum(sum),
            .cout(cout)
            );
            
integer i;
initial begin 
    $dumpfile("output.vcd");
    $dumpvars(0,tb);
            $monitor("Time =%0t|a=%b|b=%b|cin=%b|sum=%b|cout=%b",$time,a,b,cin,sum,cout);
            for(i=0;i<256;i=i+1) begin
                {a,b,cin} =i;
                #10;
             if({cout,sum} !== (a+b+cin))
                $display("ERROR: a=%b b=%b cin=%b | Expected=%b | Got=%b",
                         a, b, cin, (a + b + cin), {cout, sum});
            else 
                $display("PASS: a=%b b=%b cin=%b | sum=%b cout=%b",
                         a, b, cin, sum, cout);
            end
            $display("All test cases completed.");

        $finish;
            end
            
                       
endmodule

RAC/output.vcd
$date
	Sat Sep 12 19:02:02 2026
$end
$version
	Icarus Verilog
$end
$timescale
	1ps
$end
$scope module tb $end
$var wire 4 ! sum [3:0] $end
$var wire 1 " cout $end
$var reg 4 # a [3:0] $end
$var reg 4 $ b [3:0] $end
$var reg 1 % cin $end
$var integer 32 & i [31:0] $end
$scope module uut $end
$var wire 4 ' a [3:0] $end
$var wire 4 ( b [3:0] $end
$var wire 1 % cin $end
$var wire 4 ) sum [3:0] $end
$var wire 1 " cout $end
$var wire 1 * c3 $end
$var wire 1 + c2 $end
$var wire 1 , c1 $end
$scope module uut0 $end
$var wire 1 - a $end
$var wire 1 . b $end
$var wire 1 / c1 $end
$var wire 1 0 c2 $end
$var wire 1 % cin $end
$var wire 1 , cout $end
$var wire 1 1 s1 $end
$var wire 1 2 sum $end
$upscope $end
$scope module uut1 $end
$var wire 1 3 a $end
$var wire 1 4 b $end
$var wire 1 5 c1 $end
$var wire 1 6 c2 $end
$var wire 1 , cin $end
$var wire 1 + cout $end
$var wire 1 7 s1 $end
$var wire 1 8 sum $end
$upscope $end
$scope module uut2 $end
$var wire 1 9 a $end
$var wire 1 : b $end
$var wire 1 ; c1 $end
$var wire 1 < c2 $end
$var wire 1 + cin $end
$var wire 1 * cout $end
$var wire 1 = s1 $end
$var wire 1 > sum $end
$upscope $end
$scope module uut3 $end
$var wire 1 ? a $end
$var wire 1 @ b $end
$var wire 1 A c1 $end
$var wire 1 B c2 $end
$var wire 1 * cin $end
$var wire 1 " cout $end
$var wire 1 C s1 $end
$var wire 1 D sum $end
$upscope $end
$upscope $end
$upscope $end
$enddefinitions $end
#0
$dumpvars
0D
0C
0B
0A
0@
0?
0>
0=
0<
0;
0:
09
08
07
06
05
04
03
02
01
00
0/
0.
0-
0,
0+
0*
b0 )
b0 (
b0 '
b0 &
0%
b0 $
b0 #
0"
b0 !
$end
#10000
b1 !
b1 )
12
1%
b1 &
#20000
11
1.
b1 !
b1 )
12
b1 $
b1 (
0%
b10 &
#30000
18
1,
b10 !
b10 )
02
10
1%
b11 &
#40000
01
17
0,
0.
14
b10 !
b10 )
02
00
b10 $
b10 (
0%
b100 &
#50000
b11 !
b11 )
12
1%
b101 &
#60000
11
1.
b11 !
b11 )
12
b11 $
b11 (
0%
b110 &
#70000
1>
1+
08
16
1,
b100 !
b100 )
02
10
1%
b111 &
#80000
0D
0*
0+
1>
0<
06
01
07
1=
0,
0.
04
1:
b100 !
b100 )
02
00
b100 $
b100 (
0%
b1000 &
#90000
b101 !
b101 )
12
1%
b1001 &
#100000
11
1.
b101 !
b101 )
12
b101 $
b101 (
0%
b1010 &
#110000
18
1,
b110 !
b110 )
02
10
1%
b1011 &
#120000
01
17
0,
0.
14
b110 !
b110 )
02
00
b110 $
b110 (
0%
b1100 &
#130000
b111 !
b111 )
12
1%
b1101 &
#140000
11
1.
b111 !
b111 )
12
b111 $
b111 (
0%
b1110 &
#150000
1D
1*
0>
1<
1+
08
16
1,
b1000 !
b1000 )
02
10
1%
b1111 &
#160000
0*
0"
0+
0>
0<
1D
0B
06
01
07
0=
1C
0,
0.
04
0:
1@
b1000 !
b1000 )
02
00
b1000 $
b1000 (
0%
b10000 &
#170000
b1001 !
b1001 )
12
1%
b10001 &
#180000
11
1.
b1001 !
b1001 )
12
b1001 $
b1001 (
0%
b10010 &
#190000
18
1,
b1010 !
b1010 )
02
10
1%
b10011 &
#200000
01
17
0,
0.
14
b1010 !
b1010 )
02
00
b1010 $
b1010 (
0%
b10100 &
#210000
b1011 !
b1011 )
12
1%
b10101 &
#220000
11
1.
b1011 !
b1011 )
12
b1011 $
b1011 (
0%
b10110 &
#230000
1>
1+
08
16
1,
b1100 !
b1100 )
02
10
1%
b10111 &
#240000
0"
1D
0B
0*
0+
1>
0<
06
01
07
1=
0,
0.
04
1:
b1100 !
b1100 )
02
00
b1100 $
b1100 (
0%
b11000 &
#250000
b1101 !
b1101 )
12
1%
b11001 &
#260000
11
1.
b1101 !
b1101 )
12
b1101 $
b1101 (
0%
b11010 &
#270000
18
1,
b1110 !
b1110 )
02
10
1%
b11011 &
#280000
01
17
0,
0.
14
b1110 !
b1110 )
02
00
b1110 $
b1110 (
0%
b11100 &
#290000
b1111 !
b1111 )
12
1%
b11101 &
#300000
11
1.
b1111 !
b1111 )
12
b1111 $
b1111 (
0%
b11110 &
#310000
1"
0D
1B
1*
0>
1<
1+
08
16
1,
b0 !
b0 )
02
10
1%
b11111 &
#320000
0*
0"
0+
0>
0<
0D
0B
06
07
0=
0C
0,
1-
0.
04
0:
0@
b1 !
b1 )
12
00
b1 #
b1 '
b0 $
b0 (
0%
b100000 &
#330000
18
1,
b10 !
b10 )
02
10
1%
b100001 &
#340000
18
01
1/
1,
1.
b10 !
b10 )
02
00
b1 $
b1 (
0%
b100010 &
#350000
b11 !
b11 )
12
1%
b100011 &
#360000
0>
0+
0,
18
06
11
0/
17
0.
14
b11 !
b11 )
12
b10 $
b10 (
0%
b100100 &
#370000
1>
1+
08
16
1,
b100 !
b100 )
02
10
1%
b100101 &
#380000
1>
1+
08
16
01
1/
1,
1.
b100 !
b100 )
02
00
b11 $
b11 (
0%
b100110 &
#390000
b101 !
b101 )
12
1%
b100111 &
#400000
0D
0+
0*
0,
08
06
1>
0<
11
0/
07
1=
0.
04
1:
b101 !
b101 )
12
b100 $
b100 (
0%
b101000 &
#410000
18
1,
b110 !
b110 )
02
10
1%
b101001 &
#420000
18
01
1/
1,
1.
b110 !
b110 )
02
00
b101 $
b101 (
0%
b101010 &
#430000
b111 !
b111 )
12
1%
b101011 &
#440000
0D
0*
1>
0<
0+
0,
18
06
11
0/
17
0.
14
b111 !
b111 )
12
b110 $
b110 (
0%
b101100 &
#450000
1D
1*
0>
1<
1+
08
16
1,
b1000 !
b1000 )
02
10
1%
b101101 &
#460000
1D
1*
0>
1<
1+
08
16
01
1/
1,
1.
b1000 !
b1000 )
02
00
b111 $
b111 (
0%
b101110 &
#470000
b1001 !
b1001 )
12
1%
b101111 &
#480000
0+
0*
0"
0,
08
06
0>
0<
1D
0B
11
0/
07
0=
1C
0.
04
0:
1@
b1001 !
b1001 )
12
b1000 $
b1000 (
0%
b110000 &
#490000
18
1,
b1010 !
b1010 )
02
10
1%
b110001 &
#500000
18
01
1/
1,
1.
b1010 !
b1010 )
02
00
b1001 $
b1001 (
0%
b110010 &
#510000
b1011 !
b1011 )
12
1%
b110011 &
#520000
0>
0+
0,
18
06
11
0/
17
0.
14
b1011 !
b1011 )
12
b1010 $
b1010 (
0%
b110100 &
#530000
1>
1+
08
16
1,
b1100 !
b1100 )
02
10
1%
b110101 &
#540000
1>
1+
08
16
01
1/
1,
1.
b1100 !
b1100 )
02
00
b1011 $
b1011 (
0%
b110110 &
#550000
b1101 !
b1101 )
12
1%
b110111 &
#560000
0"
1D
0B
0+
0*
0,
08
06
1>
0<
11
0/
07
1=
0.
04
1:
b1101 !
b1101 )
12
b1100 $
b1100 (
0%
b111000 &
#570000
18
1,
b1110 !
b1110 )
02
10
1%
b111001 &
#580000
18
01
1/
1,
1.
b1110 !
b1110 )
02
00
b1101 $
b1101 (
0%
b111010 &
#590000
b1111 !
b1111 )
12
1%
b111011 &
#600000
0"
1D
0B
0*
1>
0<
0+
0,
18
06
11
0/
17
0.
14
b1111 !
b1111 )
12
b1110 $
b1110 (
0%
b111100 &
#610000
1"
0D
1B
1*
0>
1<
1+
08
16
1,
b0 !
b0 )
02
10
1%
b111101 &
#620000
1"
0D
1B
1*
0>
1<
1+
08
16
01
1/
1,
1.
b0 !
b0 )
02
00
b1111 $
b1111 (
0%
b111110 &
#630000
b1 !
b1 )
12
1%
b111111 &
#640000
0+
18
06
0*
0"
0,
0>
0<
0D
0B
0/
0=
0C
0-
13
0.
04
0:
0@
b10 !
b10 )
02
b10 #
b10 '
b0 $
b0 (
0%
b1000000 &
#650000
b11 !
b11 )
12
1%
b1000001 &
#660000
11
1.
b11 !
b11 )
12
b1 $
b1 (
0%
b1000010 &
#670000
1>
1+
08
16
1,
b100 !
b100 )
02
10
1%
b1000011 &
#680000
06
01
07
15
0,
0.
14
b100 !
b100 )
02
00
b10 $
b10 (
0%
b1000100 &
#690000
b101 !
b101 )
12
1%
b1000101 &
#700000
11
1.
b101 !
b101 )
12
b11 $
b11 (
0%
b1000110 &
#710000
18
1,
b110 !
b110 )
02
10
1%
b1000111 &
#720000
0D
0*
0+
1>
0<
01
17
05
1=
0,
0.
04
1:
b110 !
b110 )
02
00
b100 $
b100 (
0%
b1001000 &
#730000
b111 !
b111 )
12
1%
b1001001 &
#740000
11
1.
b111 !
b111 )
12
b101 $
b101 (
0%
b1001010 &
#750000
1D
1*
0>
1<
1+
08
16
1,
b1000 !
b1000 )
02
10
1%
b1001011 &
#760000
06
01
07
15
0,
0.
14
b1000 !
b1000 )
02
00
b110 $
b110 (
0%
b1001100 &
#770000
b1001 !
b1001 )
12
1%
b1001101 &
#780000
11
1.
b1001 !
b1001 )
12
b111 $
b111 (
0%
b1001110 &
#790000
18
1,
b1010 !
b1010 )
02
10
1%
b1001111 &
#800000
0*
0"
0+
0>
0<
1D
0B
01
17
05
0=
1C
0,
0.
04
0:
1@
b1010 !
b1010 )
02
00
b1000 $
b1000 (
0%
b1010000 &
#810000
b1011 !
b1011 )
12
1%
b1010001 &
#820000
11
1.
b1011 !
b1011 )
12
b1001 $
b1001 (
0%
b1010010 &
#830000
1>
1+
08
16
1,
b1100 !
b1100 )
02
10
1%
b1010011 &
#840000
06
01
07
15
0,
0.
14
b1100 !
b1100 )
02
00
b1010 $
b1010 (
0%
b1010100 &
#850000
b1101 !
b1101 )
12
1%
b1010101 &
#860000
11
1.
b1101 !
b1101 )
12
b1011 $
b1011 (
0%
b1010110 &
#870000
18
1,
b1110 !
b1110 )
02
10
1%
b1010111 &
#880000
0"
1D
0B
0*
0+
1>
0<
01
17
05
1=
0,
0.
04
1:
b1110 !
b1110 )
02
00
b1100 $
b1100 (
0%
b1011000 &
#890000
b1111 !
b1111 )
12
1%
b1011001 &
#900000
11
1.
b1111 !
b1111 )
12
b1101 $
b1101 (
0%
b1011010 &
#910000
1"
0D
1B
1*
0>
1<
1+
08
16
1,
b0 !
b0 )
02
10
1%
b1011011 &
#920000
06
01
07
15
0,
0.
14
b0 !
b0 )
02
00
b1110 $
b1110 (
0%
b1011100 &
#930000
b1 !
b1 )
12
1%
b1011101 &
#940000
11
1.
b1 !
b1 )
12
b1111 $
b1111 (
0%
b1011110 &
#950000
18
1,
b10 !
b10 )
02
10
1%
b1011111 &
#960000
0*
0"
0+
0>
0<
0D
0B
17
05
0=
0C
0,
1-
0.
04
0:
0@
b11 !
b11 )
12
00
b11 #
b11 '
b0 $
b0 (
0%
b1100000 &
#970000
1>
1+
08
16
1,
b100 !
b100 )
02
10
1%
b1100001 &
#980000
1>
1+
08
16
01
1/
1,
1.
b100 !
b100 )
02
00
b1 $
b1 (
0%
b1100010 &
#990000
b101 !
b101 )
12
1%
b1100011 &
#1000000
0,
08
06
11
0/
07
15
0.
14
b101 !
b101 )
12
b10 $
b10 (
0%
b1100100 &
#1010000
18
1,
b110 !
b110 )
02
10
1%
b1100101 &
#1020000
18
01
1/
1,
1.
b110 !
b110 )
02
00
b11 $
b11 (
0%
b1100110 &
#1030000
b111 !
b111 )
12
1%
b1100111 &
#1040000
0D
0*
0,
18
06
0+
1>
0<
11
0/
17
05
1=
0.
04
1:
b111 !
b111 )
12
b100 $
b100 (
0%
b1101000 &
#1050000
1D
1*
0>
1<
1+
08
16
1,
b1000 !
b1000 )
02
10
1%
b1101001 &
#1060000
1D
1*
0>
1<
1+
08
16
01
1/
1,
1.
b1000 !
b1000 )
02
00
b101 $
b101 (
0%
b1101010 &
#1070000
b1001 !
b1001 )
12
1%
b1101011 &
#1080000
0,
08
06
11
0/
07
15
0.
14
b1001 !
b1001 )
12
b110 $
b110 (
0%
b1101100 &
#1090000
18
1,
b1010 !
b1010 )
02
10
1%
b1101101 &
#1100000
18
01
1/
1,
1.
b1010 !
b1010 )
02
00
b111 $
b111 (
0%
b1101110 &
#1110000
b1011 !
b1011 )
12
1%
b1101111 &
#1120000
0*
0"
0,
18
06
0+
0>
0<
1D
0B
11
0/
17
05
0=
1C
0.
04
0:
1@
b1011 !
b1011 )
12
b1000 $
b1000 (
0%
b1110000 &
#1130000
1>
1+
08
16
1,
b1100 !
b1100 )
02
10
1%
b1110001 &
#1140000
1>
1+
08
16
01
1/
1,
1.
b1100 !
b1100 )
02
00
b1001 $
b1001 (
0%
b1110010 &
#1150000
b1101 !
b1101 )
12
1%
b1110011 &
#1160000
0,
08
06
11
0/
07
15
0.
14
b1101 !
b1101 )
12
b1010 $
b1010 (
0%
b1110100 &
#1170000
18
1,
b1110 !
b1110 )
02
10
1%
b1110101 &
#1180000
18
01
1/
1,
1.
b1110 !
b1110 )
02
00
b1011 $
b1011 (
0%
b1110110 &
#1190000
b1111 !
b1111 )
12
1%
b1110111 &
#1200000
0"
1D
0B
0*
0,
18
06
0+
1>
0<
11
0/
17
05
1=
0.
04
1:
b1111 !
b1111 )
12
b1100 $
b1100 (
0%
b1111000 &
#1210000
1"
0D
1B
1*
0>
1<
1+
08
16
1,
b0 !
b0 )
02
10
1%
b1111001 &
#1220000
1"
0D
1B
1*
0>
1<
1+
08
16
01
1/
1,
1.
b0 !
b0 )
02
00
b1101 $
b1101 (
0%
b1111010 &
#1230000
b1 !
b1 )
12
1%
b1111011 &
#1240000
0,
08
06
11
0/
07
15
0.
14
b1 !
b1 )
12
b1110 $
b1110 (
0%
b1111100 &
#1250000
18
1,
b10 !
b10 )
02
10
1%
b1111101 &
#1260000
18
01
1/
1,
1.
b10 !
b10 )
02
00
b1111 $
b1111 (
0%
b1111110 &
#1270000
b11 !
b11 )
12
1%
b1111111 &
#1280000
0*
08
1>
0<
0"
0,
0+
0D
0B
0/
05
0C
0-
03
19
0.
04
0:
0@
b100 !
b100 )
02
b100 #
b100 '
b0 $
b0 (
0%
b10000000 &
#1290000
b101 !
b101 )
12
1%
b10000001 &
#1300000
11
1.
b101 !
b101 )
12
b1 $
b1 (
0%
b10000010 &
#1310000
18
1,
b110 !
b110 )
02
10
1%
b10000011 &
#1320000
01
17
0,
0.
14
b110 !
b110 )
02
00
b10 $
b10 (
0%
b10000100 &
#1330000
b111 !
b111 )
12
1%
b10000101 &
#1340000
11
1.
b111 !
b111 )
12
b11 $
b11 (
0%
b10000110 &
#1350000
1D
1*
0>
1<
1+
08
16
1,
b1000 !
b1000 )
02
10
1%
b10000111 &
#1360000
0+
0>
0<
06
01
07
0=
1;
0,
0.
04
1:
b1000 !
b1000 )
02
00
b100 $
b100 (
0%
b10001000 &
#1370000
b1001 !
b1001 )
12
1%
b10001001 &
#1380000
11
1.
b1001 !
b1001 )
12
b101 $
b101 (
0%
b10001010 &
#1390000
18
1,
b1010 !
b1010 )
02
10
1%
b10001011 &
#1400000
01
17
0,
0.
14
b1010 !
b1010 )
02
00
b110 $
b110 (
0%
b10001100 &
#1410000
b1011 !
b1011 )
12
1%
b10001101 &
#1420000
11
1.
b1011 !
b1011 )
12
b111 $
b111 (
0%
b10001110 &
#1430000
1>
1+
08
16
1,
b1100 !
b1100 )
02
10
1%
b10001111 &
#1440000
0"
0+
1>
0<
0*
1D
0B
06
01
07
1=
0;
1C
0,
0.
04
0:
1@
b1100 !
b1100 )
02
00
b1000 $
b1000 (
0%
b10010000 &
#1450000
b1101 !
b1101 )
12
1%
b10010001 &
#1460000
11
1.
b1101 !
b1101 )
12
b1001 $
b1001 (
0%
b10010010 &
#1470000
18
1,
b1110 !
b1110 )
02
10
1%
b10010011 &
#1480000
01
17
0,
0.
14
b1110 !
b1110 )
02
00
b1010 $
b1010 (
0%
b10010100 &
#1490000
b1111 !
b1111 )
12
1%
b10010101 &
#1500000
11
1.
b1111 !
b1111 )
12
b1011 $
b1011 (
0%
b10010110 &
#1510000
1"
0D
1B
1*
0>
1<
1+
08
16
1,
b0 !
b0 )
02
10
1%
b10010111 &
#1520000
0+
0>
0<
06
01
07
0=
1;
0,
0.
04
1:
b0 !
b0 )
02
00
b1100 $
b1100 (
0%
b10011000 &
#1530000
b1 !
b1 )
12
1%
b10011001 &
#1540000
11
1.
b1 !
b1 )
12
b1101 $
b1101 (
0%
b10011010 &
#1550000
18
1,
b10 !
b10 )
02
10
1%
b10011011 &
#1560000
01
17
0,
0.
14
b10 !
b10 )
02
00
b1110 $
b1110 (
0%
b10011100 &
#1570000
b11 !
b11 )
12
1%
b10011101 &
#1580000
11
1.
b11 !
b11 )
12
b1111 $
b1111 (
0%
b10011110 &
#1590000
1>
1+
08
16
1,
b100 !
b100 )
02
10
1%
b10011111 &
#1600000
0"
0+
1>
0<
0*
0D
0B
06
07
1=
0;
0C
0,
1-
0.
04
0:
0@
b101 !
b101 )
12
00
b101 #
b101 '
b0 $
b0 (
0%
b10100000 &
#1610000
18
1,
b110 !
b110 )
02
10
1%
b10100001 &
#1620000
18
01
1/
1,
1.
b110 !
b110 )
02
00
b1 $
b1 (
0%
b10100010 &
#1630000
b111 !
b111 )
12
1%
b10100011 &
#1640000
0D
0*
1>
0<
0+
0,
18
06
11
0/
17
0.
14
b111 !
b111 )
12
b10 $
b10 (
0%
b10100100 &
#1650000
1D
1*
0>
1<
1+
08
16
1,
b1000 !
b1000 )
02
10
1%
b10100101 &
#1660000
1D
1*
0>
1<
1+
08
16
01
1/
1,
1.
b1000 !
b1000 )
02
00
b11 $
b11 (
0%
b10100110 &
#1670000
b1001 !
b1001 )
12
1%
b10100111 &
#1680000
0+
0,
08
06
0>
0<
11
0/
07
0=
1;
0.
04
1:
b1001 !
b1001 )
12
b100 $
b100 (
0%
b10101000 &
#1690000
18
1,
b1010 !
b1010 )
02
10
1%
b10101001 &
#1700000
18
01
1/
1,
1.
b1010 !
b1010 )
02
00
b101 $
b101 (
0%
b10101010 &
#1710000
b1011 !
b1011 )
12
1%
b10101011 &
#1720000
0>
0+
0,
18
06
11
0/
17
0.
14
b1011 !
b1011 )
12
b110 $
b110 (
0%
b10101100 &
#1730000
1>
1+
08
16
1,
b1100 !
b1100 )
02
10
1%
b10101101 &
#1740000
1>
1+
08
16
01
1/
1,
1.
b1100 !
b1100 )
02
00
b111 $
b111 (
0%
b10101110 &
#1750000
b1101 !
b1101 )
12
1%
b10101111 &
#1760000
0+
0"
0,
08
06
1>
0<
0*
1D
0B
11
0/
07
1=
0;
1C
0.
04
0:
1@
b1101 !
b1101 )
12
b1000 $
b1000 (
0%
b10110000 &
#1770000
18
1,
b1110 !
b1110 )
02
10
1%
b10110001 &
#1780000
18
01
1/
1,
1.
b1110 !
b1110 )
02
00
b1001 $
b1001 (
0%
b10110010 &
#1790000
b1111 !
b1111 )
12
1%
b10110011 &
#1800000
0"
1D
0B
0*
1>
0<
0+
0,
18
06
11
0/
17
0.
14
b1111 !
b1111 )
12
b1010 $
b1010 (
0%
b10110100 &
#1810000
1"
0D
1B
1*
0>
1<
1+
08
16
1,
b0 !
b0 )
02
10
1%
b10110101 &
#1820000
1"
0D
1B
1*
0>
1<
1+
08
16
01
1/
1,
1.
b0 !
b0 )
02
00
b1011 $
b1011 (
0%
b10110110 &
#1830000
b1 !
b1 )
12
1%
b10110111 &
#1840000
0+
0,
08
06
0>
0<
11
0/
07
0=
1;
0.
04
1:
b1 !
b1 )
12
b1100 $
b1100 (
0%
b10111000 &
#1850000
18
1,
b10 !
b10 )
02
10
1%
b10111001 &
#1860000
18
01
1/
1,
1.
b10 !
b10 )
02
00
b1101 $
b1101 (
0%
b10111010 &
#1870000
b11 !
b11 )
12
1%
b10111011 &
#1880000
0>
0+
0,
18
06
11
0/
17
0.
14
b11 !
b11 )
12
b1110 $
b1110 (
0%
b10111100 &
#1890000
1>
1+
08
16
1,
b100 !
b100 )
02
10
1%
b10111101 &
#1900000
1>
1+
08
16
01
1/
1,
1.
b100 !
b100 )
02
00
b1111 $
b1111 (
0%
b10111110 &
#1910000
b101 !
b101 )
12
1%
b10111111 &
#1920000
0+
18
06
0"
0,
1>
0<
0*
0D
0B
0/
1=
0;
0C
0-
13
0.
04
0:
0@
b110 !
b110 )
02
b110 #
b110 '
b0 $
b0 (
0%
b11000000 &
#1930000
b111 !
b111 )
12
1%
b11000001 &
#1940000
11
1.
b111 !
b111 )
12
b1 $
b1 (
0%
b11000010 &
#1950000
1D
1*
0>
1<
1+
08
16
1,
b1000 !
b1000 )
02
10
1%
b11000011 &
#1960000
06
01
07
15
0,
0.
14
b1000 !
b1000 )
02
00
b10 $
b10 (
0%
b11000100 &
#1970000
b1001 !
b1001 )
12
1%
b11000101 &
#1980000
11
1.
b1001 !
b1001 )
12
b11 $
b11 (
0%
b11000110 &
#1990000
18
1,
b1010 !
b1010 )
02
10
1%
b11000111 &
#2000000
0+
0>
0<
01
17
05
0=
1;
0,
0.
04
1:
b1010 !
b1010 )
02
00
b100 $
b100 (
0%
b11001000 &
#2010000
b1011 !
b1011 )
12
1%
b11001001 &
#2020000
11
1.
b1011 !
b1011 )
12
b101 $
b101 (
0%
b11001010 &
#2030000
1>
1+
08
16
1,
b1100 !
b1100 )
02
10
1%
b11001011 &
#2040000
06
01
07
15
0,
0.
14
b1100 !
b1100 )
02
00
b110 $
b110 (
0%
b11001100 &
#2050000
b1101 !
b1101 )
12
1%
b11001101 &
#2060000
11
1.
b1101 !
b1101 )
12
b111 $
b111 (
0%
b11001110 &
#2070000
18
1,
b1110 !
b1110 )
02
10
1%
b11001111 &
#2080000
0"
0+
1>
0<
0*
1D
0B
01
17
05
1=
0;
1C
0,
0.
04
0:
1@
b1110 !
b1110 )
02
00
b1000 $
b1000 (
0%
b11010000 &
#2090000
b1111 !
b1111 )
12
1%
b11010001 &
#2100000
11
1.
b1111 !
b1111 )
12
b1001 $
b1001 (
0%
b11010010 &
#2110000
1"
0D
1B
1*
0>
1<
1+
08
16
1,
b0 !
b0 )
02
10
1%
b11010011 &
#2120000
06
01
07
15
0,
0.
14
b0 !
b0 )
02
00
b1010 $
b1010 (
0%
b11010100 &
#2130000
b1 !
b1 )
12
1%
b11010101 &
#2140000
11
1.
b1 !
b1 )
12
b1011 $
b1011 (
0%
b11010110 &
#2150000
18
1,
b10 !
b10 )
02
10
1%
b11010111 &
#2160000
0+
0>
0<
01
17
05
0=
1;
0,
0.
04
1:
b10 !
b10 )
02
00
b1100 $
b1100 (
0%
b11011000 &
#2170000
b11 !
b11 )
12
1%
b11011001 &
#2180000
11
1.
b11 !
b11 )
12
b1101 $
b1101 (
0%
b11011010 &
#2190000
1>
1+
08
16
1,
b100 !
b100 )
02
10
1%
b11011011 &
#2200000
06
01
07
15
0,
0.
14
b100 !
b100 )
02
00
b1110 $
b1110 (
0%
b11011100 &
#2210000
b101 !
b101 )
12
1%
b11011101 &
#2220000
11
1.
b101 !
b101 )
12
b1111 $
b1111 (
0%
b11011110 &
#2230000
18
1,
b110 !
b110 )
02
10
1%
b11011111 &
#2240000
0"
0+
1>
0<
0*
0D
0B
17
05
1=
0;
0C
0,
1-
0.
04
0:
0@
b111 !
b111 )
12
00
b111 #
b111 '
b0 $
b0 (
0%
b11100000 &
#2250000
1D
1*
0>
1<
1+
08
16
1,
b1000 !
b1000 )
02
10
1%
b11100001 &
#2260000
1D
1*
0>
1<
1+
08
16
01
1/
1,
1.
b1000 !
b1000 )
02
00
b1 $
b1 (
0%
b11100010 &
#2270000
b1001 !
b1001 )
12
1%
b11100011 &
#2280000
0,
08
06
11
0/
07
15
0.
14
b1001 !
b1001 )
12
b10 $
b10 (
0%
b11100100 &
#2290000
18
1,
b1010 !
b1010 )
02
10
1%
b11100101 &
#2300000
18
01
1/
1,
1.
b1010 !
b1010 )
02
00
b11 $
b11 (
0%
b11100110 &
#2310000
b1011 !
b1011 )
12
1%
b11100111 &
#2320000
0,
18
06
0+
0>
0<
11
0/
17
05
0=
1;
0.
04
1:
b1011 !
b1011 )
12
b100 $
b100 (
0%
b11101000 &
#2330000
1>
1+
08
16
1,
b1100 !
b1100 )
02
10
1%
b11101001 &
#2340000
1>
1+
08
16
01
1/
1,
1.
b1100 !
b1100 )
02
00
b101 $
b101 (
0%
b11101010 &
#2350000
b1101 !
b1101 )
12
1%
b11101011 &
#2360000
0,
08
06
11
0/
07
15
0.
14
b1101 !
b1101 )
12
b110 $
b110 (
0%
b11101100 &
#2370000
18
1,
b1110 !
b1110 )
02
10
1%
b11101101 &
#2380000
18
01
1/
1,
1.
b1110 !
b1110 )
02
00
b111 $
b111 (
0%
b11101110 &
#2390000
b1111 !
b1111 )
12
1%
b11101111 &
#2400000
0"
0,
18
06
0+
1>
0<
0*
1D
0B
11
0/
17
05
1=
0;
1C
0.
04
0:
1@
b1111 !
b1111 )
12
b1000 $
b1000 (
0%
b11110000 &
#2410000
1"
0D
1B
1*
0>
1<
1+
08
16
1,
b0 !
b0 )
02
10
1%
b11110001 &
#2420000
1"
0D
1B
1*
0>
1<
1+
08
16
01
1/
1,
1.
b0 !
b0 )
02
00
b1001 $
b1001 (
0%
b11110010 &
#2430000
b1 !
b1 )
12
1%
b11110011 &
#2440000
0,
08
06
11
0/
07
15
0.
14
b1 !
b1 )
12
b1010 $
b1010 (
0%
b11110100 &
#2450000
18
1,
b10 !
b10 )
02
10
1%
b11110101 &
#2460000
18
01
1/
1,
1.
b10 !
b10 )
02
00
b1011 $
b1011 (
0%
b11110110 &
#2470000
b11 !
b11 )
12
1%
b11110111 &
#2480000
0,
18
06
0+
0>
0<
11
0/
17
05
0=
1;
0.
04
1:
b11 !
b11 )
12
b1100 $
b1100 (
0%
b11111000 &
#2490000
1>
1+
08
16
1,
b100 !
b100 )
02
10
1%
b11111001 &
#2500000
1>
1+
08
16
01
1/
1,
1.
b100 !
b100 )
02
00
b1101 $
b1101 (
0%
b11111010 &
#2510000
b101 !
b101 )
12
1%
b11111011 &
#2520000
0,
08
06
11
0/
07
15
0.
14
b101 !
b101 )
12
b1110 $
b1110 (
0%
b11111100 &
#2530000
18
1,
b110 !
b110 )
02
10
1%
b11111101 &
#2540000
18
01
1/
1,
1.
b110 !
b110 )
02
00
b1111 $
b1111 (
0%
b11111110 &
#2550000
b111 !
b111 )
12
1%
b11111111 &
#2560000
b100000000 &
